Workbook

Sheet Dashboard
A2: Football forward performance
A4: Only verified 90-minute results settle a selection. Win rate = wins / settled selections.
A6: Metric | B6: Result | D6: Tier | E6: Settled | F6: Win rate
A7: Archived selections | B7: =Breakdowns!C6 -> 22 | D7: STRICT | E7: =Breakdowns!D7 -> 6 | F7: =Breakdowns!H7 -> 1
A8: Settled selections | B8: =Breakdowns!D6 -> 11 | D8: PROVISIONAL | E8: =Breakdowns!D8 -> 5 | F8: =Breakdowns!H8 -> 0.4
A9: Wins | B9: =Breakdowns!E6 -> 8
A10: Losses | B10: =Breakdowns!F6 -> 3 | D10: Evidence status
A11: Pending / unverified | B11: =Breakdowns!G6 -> 11 | D11: =IF(B8=0,"Awaiting verified results",IF(B8<30,"Early sample: continue forward testing","Review calibration and ROI by segment")) -> Early sample: continue forward testing
A12: Win rate | B12: =Breakdowns!H6 -> 0.72727273
A13: Simulated flat-stake ROI | B13: =Breakdowns!K6 -> 0.01 | D13: Results coverage
A14: Simulated net profit (units) | B14: =Breakdowns!J6 -> 0.11 | D14: 11 settled; 11 pending / unverified
A15: Selection Brier (lower is better) | B15: =Breakdowns!L6 -> 0.21593197
A16: 1X2 forecast accuracy | B16: =IF(COUNT(Predictions!H6:H147)=0,"n.a.",AVERAGE(Predictions!H6:H147)) -> 0.64705882 | D16: Forecast metric | E16: Samples | F16: Accuracy
A17: 1X2 multiclass Brier | B17: =IF(COUNT(Predictions!I6:I147)=0,"n.a.",AVERAGE(Predictions!I6:I147)) -> 0.54248256 | D17: Over 1.5 | E17: =COUNT(Predictions!J6:J147) -> 34 | F17: =IF(E17=0,"n.a.",AVERAGE(Predictions!J6:J147)) -> 0.91176471
A18: Win-rate 95% lower | B18: =IF(B8=0,"n.a.",(B12+1.96^2/(2*B8)-1.96*SQRT(B12*(1-B12)/B8+1.96^2/(4*B8^2)))/(1+1.96^2/B8)) -> 0.43434971 | D18: Under 3.5 | E18: =COUNT(Predictions!K6:K147) -> 34 | F18: =IF(E18=0,"n.a.",AVERAGE(Predictions!K6:K147)) -> 0.55882353
A19: Win-rate 95% upper | B19: =IF(B8=0,"n.a.",(B12+1.96^2/(2*B8)+1.96*SQRT(B12*(1-B12)/B8+1.96^2/(4*B8^2)))/(1+1.96^2/B8)) -> 0.90254119 | D19: BTTS Yes | E19: =COUNT(Predictions!L6:L147) -> 34 | F19: =IF(E19=0,"n.a.",AVERAGE(Predictions!L6:L147)) -> 0.52941176
D20: BTTS No | E20: =COUNT(Predictions!M6:M147) -> 34 | F20: =IF(E20=0,"n.a.",AVERAGE(Predictions!M6:M147)) -> 0.52941176
A21: Conclusion: 8 wins from 11 settled selections. Early evidence; do not retune from this sample.
A23: ROI Plan: editable bankroll and flat stake. ROI excludes settled entries with missing odds.
A24: Model review: compare tiers, markets, leagues and policies in Breakdowns. Decisions remain manual.
A25: Weeks use the ISO calendar, not competition matchweek numbers.
A26: Result-source issues: none recorded
A27: Review UTC: 2026-10-15T15:13:16.300635+00:00
A28: PROVISIONAL is a research watchlist. Positive simulated ROI does not establish profitability.
A29: Review notes use 30 scored samples as a prompt, not statistical proof. Reassess on a future holdout.
A31: Experiment readiness | D31: Collection health
A33: Monitoring and next actions
A34: Check | B34: Status | D34: Next action
A35: Experiments ready | B35: 0 | D35: Continue generating and pushing forecasts
A36: Unavailable / stale reports | B36: 0 | D36: No stale experiment reports recorded
A37: Missing near-close quotes | B37: 25 | D37: Check local collection and push quotes; counts overlap across bookmakers
A38: Rejected quote files | B38: 0 | D38: No rejected quote files recorded
A39: Latest frozen capture | B39: 2026-10-15 13:21:36 UTC | D39: See Capture Details for all six experiment states
A41: Weekly samples and profit | D41: Metric definitions

Sheet Experiments
A2: Experiment readiness
A4: Readiness invites review, including negative findings. Production changes still require approval.
A5: Experiment | B5: Status | C5: Collected | D5: Evidence unit | E5: Required sample | F5: Time collected / required | G5: Verified coverage | H5: Review scope | I5: Remaining requirements / next action | J5: Evidence finding
A6: Goal-market blend | B6: Collect more data | C6: 48 | D6: Settled observations | E6: 30 settled observations | F6: 2 / 28 days | G6: Not applicable | H6: Initial review only | I6: 26 more days | J6: Initial review only
A7: Market-led forecasts | B7: Collect more data | C7: 32 | D7: Settled observations | E7: 30 settled observations | F7: 2 / 28 days | G7: Not applicable | H7: Initial review only | I7: 26 more days | J7: Initial review only
A8: Recency comparison | B8: Collect more data | C8: 30 | D8: Settled observations | E8: 30 settled observations | F8: 1 / 28 days | G8: Not applicable | H8: Initial review only | I8: 27 more days | J8: Initial review only
A9: EV filter sensitivity | B9: Collect more data | C9: 3 | D9: Settled observations | E9: 30 settled observations | F9: 1 / 28 days | G9: Not applicable | H9: Initial review only | I9: 27 more observations; 27 more days | J9: Initial review only
A10: 85% market weight | B10: Collect more data | C10: 0 | D10: Paired fixtures | E10: 300 paired fixtures | F10: 0 / 6 ISO weeks | G10: Unavailable | H10: Approval review | I10: 300 more paired fixtures; 6 more ISO weeks; Verified coverage unavailable | J10: No clear promotion evidence
A11: Pinnacle totals anchor | B11: Collect more data | C11: 0 | D11: Paired fixtures | E11: 300 paired fixtures | F11: 0 / 6 ISO weeks | G11: Unavailable | H11: Approval review | I11: 300 more paired fixtures; 6 more ISO weeks; Verified coverage unavailable | J11: No clear promotion evidence
A12: Stronger regularisation (L2=3) | B12: Collect more data | C12: 0 | D12: Paired fixtures | E12: 300 paired fixtures | F12: 0 / 6 ISO weeks | G12: Unavailable | H12: Approval review | I12: 300 more paired fixtures; 6 more ISO weeks; Verified coverage unavailable | J12: No clear promotion evidence
A13: Fixed half-life (480 days) | B13: Collect more data | C13: 0 | D13: Paired fixtures | E13: 300 paired fixtures | F13: 0 / 6 ISO weeks | G13: Unavailable | H13: Approval review | I13: 300 more paired fixtures; 6 more ISO weeks; Verified coverage unavailable | J13: No clear promotion evidence
A14: Probability / calibration policy | B14: Collect more data | C14: 0 | D14: Paired fixtures | E14: 300 paired fixtures | F14: 0 / 6 ISO weeks | G14: 0 | H14: Approval review | I14: 300 more paired fixtures; 6 more ISO weeks; Coverage below 80% | J14: Initial review only
A16: The original four sidecars count observations, not necessarily independent fixtures. Do not add their sample counts together.
A17: Coverage and time gates must also pass. Reaching a sample count alone does not make a candidate ready.
A19: Back to dashboard
A22: Probability and calibration policies — fixed comparisons
A23: STRICT is primary. ROI is simulated; different selected cohorts are not paired forecast tests. See the detailed report before drawing conclusions.
A24: Variant | B24: Tier | C24: Selected | D24: Settled | E24: Net ROI | F24: Brier | G24: Log loss | H24: Calibration gap | I24: Drawdown (units) | J24: Strict profit delta / fixture 95% interval
A25: control | B25: STRICT | C25: 1 | D25: 0 | E25: Unavailable | F25: Unavailable | G25: Unavailable | H25: Unavailable | I25: Unavailable | J25: Collect more data
A26: control | B26: PROVISIONAL | C26: 1 | D26: 0 | E26: Unavailable | F26: Unavailable | G26: Unavailable | H26: Unavailable | I26: Unavailable | J26: Not applicable
A27: control | B27: ALL | C27: 2 | D27: 0 | E27: Unavailable | F27: Unavailable | G27: Unavailable | H27: Unavailable | I27: Unavailable | J27: Not applicable
A28: blended_lower | B28: STRICT | C28: 3 | D28: 0 | E28: Unavailable | F28: Unavailable | G28: Unavailable | H28: Unavailable | I28: Unavailable | J28: Collect more data
A29: blended_lower | B29: PROVISIONAL | C29: 1 | D29: 0 | E29: Unavailable | F29: Unavailable | G29: Unavailable | H29: Unavailable | I29: Unavailable | J29: Not applicable
A30: blended_lower | B30: ALL | C30: 4 | D30: 0 | E30: Unavailable | F30: Unavailable | G30: Unavailable | H30: Unavailable | I30: Unavailable | J30: Not applicable
A31: blended_higher | B31: STRICT | C31: 0 | D31: 0 | E31: Unavailable | F31: Unavailable | G31: Unavailable | H31: Unavailable | I31: Unavailable | J31: Collect more data
A32: blended_higher | B32: PROVISIONAL | C32: 1 | D32: 0 | E32: Unavailable | F32: Unavailable | G32: Unavailable | H32: Unavailable | I32: Unavailable | J32: Not applicable
A33: blended_higher | B33: ALL | C33: 1 | D33: 0 | E33: Unavailable | F33: Unavailable | G33: Unavailable | H33: Unavailable | I33: Unavailable | J33: Not applicable
A34: raw_lower | B34: STRICT | C34: 1 | D34: 0 | E34: Unavailable | F34: Unavailable | G34: Unavailable | H34: Unavailable | I34: Unavailable | J34: Collect more data
A35: raw_lower | B35: PROVISIONAL | C35: 1 | D35: 0 | E35: Unavailable | F35: Unavailable | G35: Unavailable | H35: Unavailable | I35: Unavailable | J35: Not applicable
A36: raw_lower | B36: ALL | C36: 2 | D36: 0 | E36: Unavailable | F36: Unavailable | G36: Unavailable | H36: Unavailable | I36: Unavailable | J36: Not applicable
... A51: penalty_stronger | B51: ALL | C51: 2 | D51: 0 | E51: Unavailable | F51: Unavailable | G51: Unavailable | H51: Unavailable | I51: Unavailable | J51: Not applicable

Sheet Pipeline Health
A2: Pipeline health
A4: Health describes collection and evidence coverage. Recent result dates alone do not verify source completeness.
A5: Review UTC: 2026-10-15T15:13:16.300635+00:00
A7: Training data freshness
A8: League | B8: Latest result | C8: Training matches | D8: Days since result | E8: Source status | F8: Next check
A9: Bundesliga | B9: 2026-10-11 | C9: 963 | D9: 4 | E9: Result date only not completeness verified | F9: Source completeness unverified
A10: EPL | B10: 2026-10-12 | C10: 1200 | D10: 3 | E10: Result date only not completeness verified | F10: Source completeness unverified
A11: LaLiga | B11: 2026-10-12 | C11: 1218 | D11: 3 | E11: Result date only not completeness verified | F11: Source completeness unverified
A12: Ligue1 | B12: 2026-10-11 | C12: 972 | D12: 4 | E12: Result date only not completeness verified | F12: Source completeness unverified
A13: SerieA | B13: 2026-10-12 | C13: 1200 | D13: 3 | E13: Result date only not completeness verified | F13: Source completeness unverified
A14: UCL | B14: 2026-10-14 | C14: 539 | D14: 1 | E14: Current within provider schedule | F14: See source health report
A17: Near-close quote coverage
A18: Bookmaker | B18: Covered selections | C18: Missing selections | D18: Pending selections | E18: Mean fair-close EV | F18: Same-book offer CLV
A19: 1xbet | B19: 0 | C19: 13 | D19: 9 | E19: Unavailable | F19: Unavailable
A20: pinnacle | B20: 1 | C20: 12 | D20: 9 | E20: 0.053178845 | F20: Unavailable
A23: Observed near-close quotes are not guaranteed official closes. Accepted bet prices and execution remain unverified.
A25: Latest shortlist quote audit
A26: Check | B26: Recorded value
A27: Account availability | B27: Not verified with bookmaker accounts
A28: Bookmakers: 1xBet | B28: 2
A29: Costs recorded | B29: 2
A30: Exchange quotes | B30: 0
A31: Missing quote age | B31: 0
A32: Quote age over 24h | B32: 0
A33: Selected quotes | B33: 2
A36: Forecast capture coverage
A37: Experiment | B37: Capture state | C37: Snapshot count
A38: Goal-market blend | B38: Captured | C38: 14
A39: Goal-market blend | B39: Legacy not recorded | C39: 14
A40: Market-led forecasts | B40: Captured | C40: 14
A41: Market-led forecasts | B41: Legacy not recorded | C41: 14
A42: Recency comparison | B42: Captured | C42: 10
A43: Recency comparison | B43: Legacy not recorded | C43: 18
A44: EV filter sensitivity | B44: Captured | C44: 9
A45: EV filter sensitivity | B45: Legacy not recorded | C45: 19
A46: 85% market weight | B46: Captured | C46: 7
A47: 85% market weight | B47: Legacy not recorded | C47: 20
A48: 85% market weight | B48: Present but rejected | C48: 1
A49: Pinnacle totals anchor | B49: Captured | C49: 7
... A55: Probability / calibration policy | B55: Present but rejected | C55: 1
A58: EV sensitivity results
A59: EV floor | B59: Tier | C59: Selected | D59: Settled | E59: Simulated ROI | F59: Drawdown (units)
A60: 0.015 | B60: ALL | C60: 7 | D60: 3 | E60: 0.36 | F60: 0
A61: 0.015 | B61: STRICT | C61: 6 | D61: 3 | E61: 0.36 | F61: 0
A62: 0.015 | B62: PROVISIONAL | C62: 1 | D62: 0
A63: 0.03 | B63: ALL | C63: 7 | D63: 3 | E63: 0.36 | F63: 0
A64: 0.03 | B64: STRICT | C64: 6 | D64: 3 | E64: 0.36 | F64: 0
A65: 0.03 | B65: PROVISIONAL | C65: 1 | D65: 0
A66: 0.05 | B66: ALL | C66: 6 | D66: 3 | E66: 0.36 | F66: 0
A67: 0.05 | B67: STRICT | C67: 5 | D67: 3 | E67: 0.36 | F67: 0
A68: 0.05 | B68: PROVISIONAL | C68: 1 | D68: 0
A71: Daily review observations
A72: Review date | B72: Graded | C72: Win rate | D72: Simulated ROI | E72: Brier
A73: 2026-10-13 | B73: 9 | C73: 0.666667 | D73: -0.096667 | E73: 0.250532
A74: 2026-10-14 | B74: 11 | C74: 0.727273 | D74: 0.01 | E74: 0.215932
A75: 2026-10-15 | B75: 11 | C75: 0.727273 | D75: 0.01 | E75: 0.215932
A78: Dependency versions
A79: Dependency | B79: Version
A80: PyYAML | B80: 6.0.3
A81: coverage | B81: 7.16.2
A82: numpy | B82: 2.5.4
A83: pandas | B83: 3.0.6
A84: python | B84: 3.12.15
A85: python-dotenv | B85: 1.2.4
A86: requests | B86: 2.34.2
A87: scipy | B87: 1.18.1
A90: Back to dashboard

Sheet Weekly Trends
A2: Weekly performance
A4: ISO calendar weeks. All archived selection policies and tiers; profit uses offered prices and simulated stakes.
A5: ISO week | B5: Settled selections | C5: Priced selections | D5: Simulated profit (units) | E5: Cumulative profit (units) | F5: Win rate
A6: =Breakdowns!B24 -> 2026-W41 | B6: =Breakdowns!D24 -> 4 | C6: =COUNTIFS(Selections!$P$6:$P$27,A6,Selections!$M$6:$M$27,">0") -> 4 | D6: =IF(C6=0,"n.a.",Breakdowns!J24) -> -1.48 | E6: =IF(SUM($C$6:C6)=0,"n.a.",SUM($D$6:D6)) -> -1.48 | F6: =Breakdowns!H24 -> 0.5
A7: =Breakdowns!B25 -> 2026-W42 | B7: =Breakdowns!D25 -> 7 | C7: =COUNTIFS(Selections!$P$6:$P$27,A7,Selections!$M$6:$M$27,">0") -> 7 | D7: =IF(C7=0,"n.a.",Breakdowns!J25) -> 1.59 | E7: =IF(SUM($C$6:C7)=0,"n.a.",SUM($D$6:D7)) -> 0.11 | F7: =Breakdowns!H25 -> 0.85714286
A8: =Breakdowns!B26 -> 2026-W43 | B8: =Breakdowns!D26 -> 0 | C8: =COUNTIFS(Selections!$P$6:$P$27,A8,Selections!$M$6:$M$27,">0") -> 0 | D8: =IF(C8=0,"n.a.",Breakdowns!J26) -> n.a. | E8: =IF(SUM($C$6:C8)=0,"n.a.",SUM($D$6:D8)) -> 0.11 | F8: =Breakdowns!H26 -> n.a.
A10: Pending selections are excluded from rates. Weeks with no priced settled selections have no realised evidence of profit.

Sheet Breakdowns
A2: Breakdowns
A4: Calculated from the archived selection ledger. Pending outcomes are excluded from rates.
A5: Dimension | B5: Group | C5: Archived | D5: Settled | E5: Wins | F5: Losses | G5: Pending | H5: Win rate | I5: Staked units | J5: Profit units | K5: ROI | L5: Brier | M5: Mean forecast | N5: Observed rate | O5: Calibration gap | P5: Probability samples | Q5: Review
A6: All | B6: All selections | C6: =COUNTA(Selections!$A$6:$A$27) -> 22 | D6: =(COUNTIFS(Selections!$K$6:$K$27,"WON")+COUNTIFS(Selections!$K$6:$K$27,"LOST")) -> 11 | E6: =COUNTIFS(Selections!$K$6:$K$27,"WON") -> 8 | F6: =COUNTIFS(Selections!$K$6:$K$27,"LOST") -> 3 | G6: =COUNTA(Selections!$A$6:$A$27)-(COUNTIFS(Selections!$K$6:$K$27,"WON")+COUNTIFS(Selections!$K$6:$K$27,"LOST")) -> 11 | H6: =IF((COUNTIFS(Selections!$K$6:$K$27,"WON")+COUNTIFS(Selections!$K$6:$K$27,"LOST"))=0,"n.a.",COUNTIFS(Selections!$K$6:$K$27,"WON")/(COUNTIFS(Selections!$K$6:$K$27,"WON")+COUNTIFS(Selections!$K$6:$K$27,"LOST"))) -> 0.72727273 | I6: =SUM(Selections!$M$6:$M$27) -> 11 | J6: =SUM(Selections!$N$6:$N$27) -> 0.11 | K6: =IF(SUM(Selections!$M$6:$M$27)=0,"n.a.",SUM(Selections!$N$6:$N$27)/SUM(Selections!$M$6:$M$27)) -> 0.01 | L6: =IF(SUM(Selections!$T$6:$T$27)=0,"n.a.",SUM(Selections!$O$6:$O$27)/SUM(Selections!$T$6:$T$27)) -> 0.21593197 | M6: =IF(SUM(Selections!$T$6:$T$27)=0,"n.a.",SUM(Selections!$S$6:$S$27)/SUM(Selections!$T$6:$T$27)) -> 0.80129825 | N6: =IF(SUM(Selections!$T$6:$T$27)=0,"n.a.",(SUMIFS(Selections!$L$6:$L$27,Selections!$T$6:$T$27,1))/SUM(Selections!$T$6:$T$27)) -> 0.72727273 | O6: =IF(SUM(Selections!$T$6:$T$27)=0,"n.a.",(SUM(Selections!$S$6:$S$27)-(SUMIFS(Selections!$L$6:$L$27,Selections!$T$6:$T$27,1)))/SUM(Selections!$T$6:$T$27)) -> 0.074025523 | P6: =SUM(Selections!$T$6:$T$27) -> 11 | Q6: =IF(P6<30,"Collect more scored forecasts (n="&P6&").",IF(O6>0.1,"Review overconfidence on a future holdout.",IF(K6<0,"Review prices and EV on a future holdout.","Continue forward testing. No automatic model change."))) -> Collect more scored forecasts (n=11).
A7: Tier | B7: STRICT | C7: =COUNTIFS(Selections!$F$6:$F$27,"STRICT") -> 12 | D7: =(COUNTIFS(Selections!$F$6:$F$27,"STRICT",Selections!$K$6:$K$27,"WON")+COUNTIFS(Selections!$F$6:$F$27,"STRICT",Selections!$K$6:$K$27,"LOST")) -> 6 | E7: =COUNTIFS(Selections!$F$6:$F$27,"STRICT",Selections!$K$6:$K$27,"WON") -> 6 | F7: =COUNTIFS(Selections!$F$6:$F$27,"STRICT",Selections!$K$6:$K$27,"LOST") -> 0 | G7: =COUNTIFS(Selections!$F$6:$F$27,"STRICT")-(COUNTIFS(Selections!$F$6:$F$27,"STRICT",Selections!$K$6:$K$27,"WON")+COUNTIFS(Selections!$F$6:$F$27,"STRICT",Selections!$K$6:$K$27,"LOST")) -> 6 | H7: =IF((COUNTIFS(Selections!$F$6:$F$27,"STRICT",Selections!$K$6:$K$27,"WON")+COUNTIFS(Selections!$F$6:$F$27,"STRICT",Selections!$K$6:$K$27,"LOST"))=0,"n.a.",COUNTIFS(Selections!$F$6:$F$27,"STRICT",Selections!$K$6:$K$27,"WON")/(COUNTIFS(Selections!$F$6:$F$27,"STRICT",Selections!$K$6:$K$27,"WON")+COUNTIFS(Selections!$F$6:$F$27,"STRICT",Selections!$K$6:$K$27,"LOST"))) -> 1 | I7: =SUMIFS(Selections!$M$6:$M$27,Selections!$F$6:$F$27,"STRICT") -> 6 | J7: =SUMIFS(Selections!$N$6:$N$27,Selections!$F$6:$F$27,"STRICT") -> 2.59 | K7: =IF(SUMIFS(Selections!$M$6:$M$27,Selections!$F$6:$F$27,"STRICT")=0,"n.a.",SUMIFS(Selections!$N$6:$N$27,Selections!$F$6:$F$27,"STRICT")/SUMIFS(Selections!$M$6:$M$27,Selections!$F$6:$F$27,"STRICT")) -> 0.43166667 | L7: =IF(SUMIFS(Selections!$T$6:$T$27,Selections!$F$6:$F$27,"STRICT")=0,"n.a.",SUMIFS(Selections!$O$6:$O$27,Selections!$F$6:$F$27,"STRICT")/SUMIFS(Selections!$T$6:$T$27,Selections!$F$6:$F$27,"STRICT")) -> 0.05977136 | M7: =IF(SUMIFS(Selections!$T$6:$T$27,Selections!$F$6:$F$27,"STRICT")=0,"n.a.",SUMIFS(Selections!$S$6:$S$27,Selections!$F$6:$F$27,"STRICT")/SUMIFS(Selections!$T$6:$T$27,Selections!$F$6:$F$27,"STRICT")) -> 0.78215519 | N7: =IF(SUMIFS(Selections!$T$6:$T$27,Selections!$F$6:$F$27,"STRICT")=0,"n.a.",(SUMIFS(Selections!$L$6:$L$27,Selections!$F$6:$F$27,"STRICT",Selections!$T$6:$T$27,1))/SUMIFS(Selections!$T$6:$T$27,Selections!$F$6:$F$27,"STRICT")) -> 1 | O7: =IF(SUMIFS(Selections!$T$6:$T$27,Selections!$F$6:$F$27,"STRICT")=0,"n.a.",(SUMIFS(Selections!$S$6:$S$27,Selections!$F$6:$F$27,"STRICT")-(SUMIFS(Selections!$L$6:$L$27,Selections!$F$6:$F$27,"STRICT",Selections!$T$6:$T$27,1)))/SUMIFS(Selections!$T$6:$T$27,Selections!$F$6:$F$27,"STRICT")) -> -0.21784481 | P7: =SUMIFS(Selections!$T$6:$T$27,Selections!$F$6:$F$27,"STRICT") -> 6 | Q7: =IF(P7<30,"Collect more scored forecasts (n="&P7&").",IF(O7>0.1,"Review overconfidence on a future holdout.",IF(K7<0,"Review prices and EV on a future holdout.","Continue forward testing. No automatic model change."))) -> Collect more scored forecasts (n=6).
A8: Tier | B8: PROVISIONAL | C8: =COUNTIFS(Selections!$F$6:$F$27,"PROVISIONAL") -> 10 | D8: =(COUNTIFS(Selections!$F$6:$F$27,"PROVISIONAL",Selections!$K$6:$K$27,"WON")+COUNTIFS(Selections!$F$6:$F$27,"PROVISIONAL",Selections!$K$6:$K$27,"LOST")) -> 5 | E8: =COUNTIFS(Selections!$F$6:$F$27,"PROVISIONAL",Selections!$K$6:$K$27,"WON") -> 2 | F8: =COUNTIFS(Selections!$F$6:$F$27,"PROVISIONAL",Selections!$K$6:$K$27,"LOST") -> 3 | G8: =COUNTIFS(Selections!$F$6:$F$27,"PROVISIONAL")-(COUNTIFS(Selections!$F$6:$F$27,"PROVISIONAL",Selections!$K$6:$K$27,"WON")+COUNTIFS(Selections!$F$6:$F$27,"PROVISIONAL",Selections!$K$6:$K$27,"LOST")) -> 5 | H8: =IF((COUNTIFS(Selections!$F$6:$F$27,"PROVISIONAL",Selections!$K$6:$K$27,"WON")+COUNTIFS(Selections!$F$6:$F$27,"PROVISIONAL",Selections!$K$6:$K$27,"LOST"))=0,"n.a.",COUNTIFS(Selections!$F$6:$F$27,"PROVISIONAL",Selections!$K$6:$K$27,"WON")/(COUNTIFS(Selections!$F$6:$F$27,"PROVISIONAL",Selections!$K$6:$K$27,"WON")+COUNTIFS(Selections!$F$6:$F$27,"PROVISIONAL",Selections!$K$6:$K$27,"LOST"))) -> 0.4 | I8: =SUMIFS(Selections!$M$6:$M$27,Selections!$F$6:$F$27,"PROVISIONAL") -> 5 | J8: =SUMIFS(Selections!$N$6:$N$27,Selections!$F$6:$F$27,"PROVISIONAL") -> -2.48 | K8: =IF(SUMIFS(Selections!$M$6:$M$27,Selections!$F$6:$F$27,"PROVISIONAL")=0,"n.a.",SUMIFS(Selections!$N$6:$N$27,Selections!$F$6:$F$27,"PROVISIONAL")/SUMIFS(Selections!$M$6:$M$27,Selections!$F$6:$F$27,"PROVISIONAL")) -> -0.496 | L8: =IF(SUMIFS(Selections!$T$6:$T$27,Selections!$F$6:$F$27,"PROVISIONAL")=0,"n.a.",SUMIFS(Selections!$O$6:$O$27,Selections!$F$6:$F$27,"PROVISIONAL")/SUMIFS(Selections!$T$6:$T$27,Selections!$F$6:$F$27,"PROVISIONAL")) -> 0.40332469 | M8: =IF(SUMIFS(Selections!$T$6:$T$27,Selections!$F$6:$F$27,"PROVISIONAL")=0,"n.a.",SUMIFS(Selections!$S$6:$S$27,Selections!$F$6:$F$27,"PROVISIONAL")/SUMIFS(Selections!$T$6:$T$27,Selections!$F$6:$F$27,"PROVISIONAL")) -> 0.82426992 | N8: =IF(SUMIFS(Selections!$T$6:$T$27,Selections!$F$6:$F$27,"PROVISIONAL")=0,"n.a.",(SUMIFS(Selections!$L$6:$L$27,Selections!$F$6:$F$27,"PROVISIONAL",Selections!$T$6:$T$27,1))/SUMIFS(Selections!$T$6:$T$27,Selections!$F$6:$F$27,"PROVISIONAL")) -> 0.4 | O8: =IF(SUMIFS(Selections!$T$6:$T$27,Selections!$F$6:$F$27,"PROVISIONAL")=0,"n.a.",(SUMIFS(Selections!$S$6:$S$27,Selections!$F$6:$F$27,"PROVISIONAL")-(SUMIFS(Selections!$L$6:$L$27,Selections!$F$6:$F$27,"PROVISIONAL",Selections!$T$6:$T$27,1)))/SUMIFS(Selections!$T$6:$T$27,Selections!$F$6:$F$27,"PROVISIONAL")) -> 0.42426992 | P8: =SUMIFS(Selections!$T$6:$T$27,Selections!$F$6:$F$27,"PROVISIONAL") -> 5 | Q8: =IF(P8<30,"Collect more scored forecasts (n="&P8&").",IF(O8>0.1,"Review overconfidence on a future holdout.",IF(K8<0,"Review prices and EV on a future holdout.","Continue forward testing. No automatic model change."))) -> Collect more scored forecasts (n=5).
A9: League | B9: Bundesliga | C9: =COUNTIFS(Selections!$C$6:$C$27,"Bundesliga") -> 1 | D9: =(COUNTIFS(Selections!$C$6:$C$27,"Bundesliga",Selections!$K$6:$K$27,"WON")+COUNTIFS(Selections!$C$6:$C$27,"Bundesliga",Selections!$K$6:$K$27,"LOST")) -> 0 | E9: =COUNTIFS(Selections!$C$6:$C$27,"Bundesliga",Selections!$K$6:$K$27,"WON") -> 0 | F9: =COUNTIFS(Selections!$C$6:$C$27,"Bundesliga",Selections!$K$6:$K$27,"LOST") -> 0 | G9: =COUNTIFS(Selections!$C$6:$C$27,"Bundesliga")-(COUNTIFS(Selections!$C$6:$C$27,"Bundesliga",Selections!$K$6:$K$27,"WON")+COUNTIFS(Selections!$C$6:$C$27,"Bundesliga",Selections!$K$6:$K$27,"LOST")) -> 1 | H9: =IF((COUNTIFS(Selections!$C$6:$C$27,"Bundesliga",Selections!$K$6:$K$27,"WON")+COUNTIFS(Selections!$C$6:$C$27,"Bundesliga",Selections!$K$6:$K$27,"LOST"))=0,"n.a.",COUNTIFS(Selections!$C$6:$C$27,"Bundesliga",Selections!$K$6:$K$27,"WON")/(COUNTIFS(Selections!$C$6:$C$27,"Bundesliga",Selections!$K$6:$K$27,"WON")+COUNTIFS(Selections!$C$6:$C$27,"Bundesliga",Selections!$K$6:$K$27,"LOST"))) -> n.a. | I9: =SUMIFS(Selections!$M$6:$M$27,Selections!$C$6:$C$27,"Bundesliga") -> 0 | J9: =SUMIFS(Selections!$N$6:$N$27,Selections!$C$6:$C$27,"Bundesliga") -> 0 | K9: =IF(SUMIFS(Selections!$M$6:$M$27,Selections!$C$6:$C$27,"Bundesliga")=0,"n.a.",SUMIFS(Selections!$N$6:$N$27,Selections!$C$6:$C$27,"Bundesliga")/SUMIFS(Selections!$M$6:$M$27,Selections!$C$6:$C$27,"Bundesliga")) -> n.a. | L9: =IF(SUMIFS(Selections!$T$6:$T$27,Selections!$C$6:$C$27,"Bundesliga")=0,"n.a.",SUMIFS(Selections!$O$6:$O$27,Selections!$C$6:$C$27,"Bundesliga")/SUMIFS(Selections!$T$6:$T$27,Selections!$C$6:$C$27,"Bundesliga")) -> n.a. | M9: =IF(SUMIFS(Selections!$T$6:$T$27,Selections!$C$6:$C$27,"Bundesliga")=0,"n.a.",SUMIFS(Selections!$S$6:$S$27,Selections!$C$6:$C$27,"Bundesliga")/SUMIFS(Selections!$T$6:$T$27,Selections!$C$6:$C$27,"Bundesliga")) -> n.a. | N9: =IF(SUMIFS(Selections!$T$6:$T$27,Selections!$C$6:$C$27,"Bundesliga")=0,"n.a.",(SUMIFS(Selections!$L$6:$L$27,Selections!$C$6:$C$27,"Bundesliga",Selections!$T$6:$T$27,1))/SUMIFS(Selections!$T$6:$T$27,Selections!$C$6:$C$27,"Bundesliga")) -> n.a. | O9: =IF(SUMIFS(Selections!$T$6:$T$27,Selections!$C$6:$C$27,"Bundesliga")=0,"n.a.",(SUMIFS(Selections!$S$6:$S$27,Selections!$C$6:$C$27,"Bundesliga")-(SUMIFS(Selections!$L$6:$L$27,Selections!$C$6:$C$27,"Bundesliga",Selections!$T$6:$T$27,1)))/SUMIFS(Selections!$T$6:$T$27,Selections!$C$6:$C$27,"Bundesliga")) -> n.a. | P9: =SUMIFS(Selections!$T$6:$T$27,Selections!$C$6:$C$27,"Bundesliga") -> 0 | Q9: =IF(P9<30,"Collect more scored forecasts (n="&P9&").",IF(O9>0.1,"Review overconfidence on a future holdout.",IF(K9<0,"Review prices and EV on a future holdout.","Continue forward testing. No automatic model change."))) -> Collect more scored forecasts (n=0).
A10: League | B10: La Liga | C10: =COUNTIFS(Selections!$C$6:$C$27,"La Liga") -> 7 | D10: =(COUNTIFS(Selections!$C$6:$C$27,"La Liga",Selections!$K$6:$K$27,"WON")+COUNTIFS(Selections!$C$6:$C$27,"La Liga",Selections!$K$6:$K$27,"LOST")) -> 2 | E10: =COUNTIFS(Selections!$C$6:$C$27,"La Liga",Selections!$K$6:$K$27,"WON") -> 2 | F10: =COUNTIFS(Selections!$C$6:$C$27,"La Liga",Selections!$K$6:$K$27,"LOST") -> 0 | G10: =COUNTIFS(Selections!$C$6:$C$27,"La Liga")-(COUNTIFS(Selections!$C$6:$C$27,"La Liga",Selections!$K$6:$K$27,"WON")+COUNTIFS(Selections!$C$6:$C$27,"La Liga",Selections!$K$6:$K$27,"LOST")) -> 5 | H10: =IF((COUNTIFS(Selections!$C$6:$C$27,"La Liga",Selections!$K$6:$K$27,"WON")+COUNTIFS(Selections!$C$6:$C$27,"La Liga",Selections!$K$6:$K$27,"LOST"))=0,"n.a.",COUNTIFS(Selections!$C$6:$C$27,"La Liga",Selections!$K$6:$K$27,"WON")/(COUNTIFS(Selections!$C$6:$C$27,"La Liga",Selections!$K$6:$K$27,"WON")+COUNTIFS(Selections!$C$6:$C$27,"La Liga",Selections!$K$6:$K$27,"LOST"))) -> 1 | I10: =SUMIFS(Selections!$M$6:$M$27,Selections!$C$6:$C$27,"La Liga") -> 2 | J10: =SUMIFS(Selections!$N$6:$N$27,Selections!$C$6:$C$27,"La Liga") -> 0.58 | K10: =IF(SUMIFS(Selections!$M$6:$M$27,Selections!$C$6:$C$27,"La Liga")=0,"n.a.",SUMIFS(Selections!$N$6:$N$27,Selections!$C$6:$C$27,"La Liga")/SUMIFS(Selections!$M$6:$M$27,Selections!$C$6:$C$27,"La Liga")) -> 0.29 | L10: =IF(SUMIFS(Selections!$T$6:$T$27,Selections!$C$6:$C$27,"La Liga")=0,"n.a.",SUMIFS(Selections!$O$6:$O$27,Selections!$C$6:$C$27,"La Liga")/SUMIFS(Selections!$T$6:$T$27,Selections!$C$6:$C$27,"La Liga")) -> 0.028808603 | M10: =IF(SUMIFS(Selections!$T$6:$T$27,Selections!$C$6:$C$27,"La Liga")=0,"n.a.",SUMIFS(Selections!$S$6:$S$27,Selections!$C$6:$C$27,"La Liga")/SUMIFS(Selections!$T$6:$T$27,Selections!$C$6:$C$27,"La Liga")) -> 0.84077105 | N10: =IF(SUMIFS(Selections!$T$6:$T$27,Selections!$C$6:$C$27,"La Liga")=0,"n.a.",(SUMIFS(Selections!$L$6:$L$27,Selections!$C$6:$C$27,"La Liga",Selections!$T$6:$T$27,1))/SUMIFS(Selections!$T$6:$T$27,Selections!$C$6:$C$27,"La Liga")) -> 1 | O10: =IF(SUMIFS(Selections!$T$6:$T$27,Selections!$C$6:$C$27,"La Liga")=0,"n.a.",(SUMIFS(Selections!$S$6:$S$27,Selections!$C$6:$C$27,"La Liga")-(SUMIFS(Selections!$L$6:$L$27,Selections!$C$6:$C$27,"La Liga",Selections!$T$6:$T$27,1)))/SUMIFS(Selections!$T$6:$T$27,Selections!$C$6:$C$27,"La Liga")) -> -0.15922895 | P10: =SUMIFS(Selections!$T$6:$T$27,Selections!$C$6:$C$27,"La Liga") -> 2 | Q10: =IF(P10<30,"Collect more scored forecasts (n="&P10&").",IF(O10>0.1,"Review overconfidence on a future holdout.",IF(K10<0,"Review prices and EV on a future holdout.","Continue forward testing. No automatic model change."))) -> Collect more scored forecasts (n=2).
A11: League | B11: Premier League | C11: =COUNTIFS(Selections!$C$6:$C$27,"Premier League") -> 6 | D11: =(COUNTIFS(Selections!$C$6:$C$27,"Premier League",Selections!$K$6:$K$27,"WON")+COUNTIFS(Selections!$C$6:$C$27,"Premier League",Selections!$K$6:$K$27,"LOST")) -> 3 | E11: =COUNTIFS(Selections!$C$6:$C$27,"Premier League",Selections!$K$6:$K$27,"WON") -> 0 | F11: =COUNTIFS(Selections!$C$6:$C$27,"Premier League",Selections!$K$6:$K$27,"LOST") -> 3 | G11: =COUNTIFS(Selections!$C$6:$C$27,"Premier League")-(COUNTIFS(Selections!$C$6:$C$27,"Premier League",Selections!$K$6:$K$27,"WON")+COUNTIFS(Selections!$C$6:$C$27,"Premier League",Selections!$K$6:$K$27,"LOST")) -> 3 | H11: =IF((COUNTIFS(Selections!$C$6:$C$27,"Premier League",Selections!$K$6:$K$27,"WON")+COUNTIFS(Selections!$C$6:$C$27,"Premier League",Selections!$K$6:$K$27,"LOST"))=0,"n.a.",COUNTIFS(Selections!$C$6:$C$27,"Premier League",Selections!$K$6:$K$27,"WON")/(COUNTIFS(Selections!$C$6:$C$27,"Premier League",Selections!$K$6:$K$27,"WON")+COUNTIFS(Selections!$C$6:$C$27,"Premier League",Selections!$K$6:$K$27,"LOST"))) -> 0 | I11: =SUMIFS(Selections!$M$6:$M$27,Selections!$C$6:$C$27,"Premier League") -> 3 | J11: =SUMIFS(Selections!$N$6:$N$27,Selections!$C$6:$C$27,"Premier League") -> -3 | K11: =IF(SUMIFS(Selections!$M$6:$M$27,Selections!$C$6:$C$27,"Premier League")=0,"n.a.",SUMIFS(Selections!$N$6:$N$27,Selections!$C$6:$C$27,"Premier League")/SUMIFS(Selections!$M$6:$M$27,Selections!$C$6:$C$27,"Premier League")) -> -1 | L11: =IF(SUMIFS(Selections!$T$6:$T$27,Selections!$C$6:$C$27,"Premier League")=0,"n.a.",SUMIFS(Selections!$O$6:$O$27,Selections!$C$6:$C$27,"Premier League")/SUMIFS(Selections!$T$6:$T$27,Selections!$C$6:$C$27,"Premier League")) -> 0.65503 | M11: =IF(SUMIFS(Selections!$T$6:$T$27,Selections!$C$6:$C$27,"Premier League")=0,"n.a.",SUMIFS(Selections!$S$6:$S$27,Selections!$C$6:$C$27,"Premier League")/SUMIFS(Selections!$T$6:$T$27,Selections!$C$6:$C$27,"Premier League")) -> 0.80845891 | N11: =IF(SUMIFS(Selections!$T$6:$T$27,Selections!$C$6:$C$27,"Premier League")=0,"n.a.",(SUMIFS(Selections!$L$6:$L$27,Selections!$C$6:$C$27,"Premier League",Selections!$T$6:$T$27,1))/SUMIFS(Selections!$T$6:$T$27,Selections!$C$6:$C$27,"Premier League")) -> 0 | O11: =IF(SUMIFS(Selections!$T$6:$T$27,Selections!$C$6:$C$27,"Premier League")=0,"n.a.",(SUMIFS(Selections!$S$6:$S$27,Selections!$C$6:$C$27,"Premier League")-(SUMIFS(Selections!$L$6:$L$27,Selections!$C$6:$C$27,"Premier League",Selections!$T$6:$T$27,1)))/SUMIFS(Selections!$T$6:$T$27,Selections!$C$6:$C$27,"Premier League")) -> 0.80845891 | P11: =SUMIFS(Selections!$T$6:$T$27,Selections!$C$6:$C$27,"Premier League") -> 3 | Q11: =IF(P11<30,"Collect more scored forecasts (n="&P11&").",IF(O11>0.1,"Review overconfidence on a future holdout.",IF(K11<0,"Review prices and EV on a future holdout.","Continue forward testing. No automatic model change."))) -> Collect more scored forecasts (n=3).
A12: League | B12: Serie A | C12: =COUNTIFS(Selections!$C$6:$C$27,"Serie A") -> 3 | D12: =(COUNTIFS(Selections!$C$6:$C$27,"Serie A",Selections!$K$6:$K$27,"WON")+COUNTIFS(Selections!$C$6:$C$27,"Serie A",Selections!$K$6:$K$27,"LOST")) -> 2 | E12: =COUNTIFS(Selections!$C$6:$C$27,"Serie A",Selections!$K$6:$K$27,"WON") -> 2 | F12: =COUNTIFS(Selections!$C$6:$C$27,"Serie A",Selections!$K$6:$K$27,"LOST") -> 0 | G12: =COUNTIFS(Selections!$C$6:$C$27,"Serie A")-(COUNTIFS(Selections!$C$6:$C$27,"Serie A",Selections!$K$6:$K$27,"WON")+COUNTIFS(Selections!$C$6:$C$27,"Serie A",Selections!$K$6:$K$27,"LOST")) -> 1 | H12: =IF((COUNTIFS(Selections!$C$6:$C$27,"Serie A",Selections!$K$6:$K$27,"WON")+COUNTIFS(Selections!$C$6:$C$27,"Serie A",Selections!$K$6:$K$27,"LOST"))=0,"n.a.",COUNTIFS(Selections!$C$6:$C$27,"Serie A",Selections!$K$6:$K$27,"WON")/(COUNTIFS(Selections!$C$6:$C$27,"Serie A",Selections!$K$6:$K$27,"WON")+COUNTIFS(Selections!$C$6:$C$27,"Serie A",Selections!$K$6:$K$27,"LOST"))) -> 1 | I12: =SUMIFS(Selections!$M$6:$M$27,Selections!$C$6:$C$27,"Serie A") -> 2 | J12: =SUMIFS(Selections!$N$6:$N$27,Selections!$C$6:$C$27,"Serie A") -> 0.91 | K12: =IF(SUMIFS(Selections!$M$6:$M$27,Selections!$C$6:$C$27,"Serie A")=0,"n.a.",SUMIFS(Selections!$N$6:$N$27,Selections!$C$6:$C$27,"Serie A")/SUMIFS(Selections!$M$6:$M$27,Selections!$C$6:$C$27,"Serie A")) -> 0.455 | L12: =IF(SUMIFS(Selections!$T$6:$T$27,Selections!$C$6:$C$27,"Serie A")=0,"n.a.",SUMIFS(Selections!$O$6:$O$27,Selections!$C$6:$C$27,"Serie A")/SUMIFS(Selections!$T$6:$T$27,Selections!$C$6:$C$27,"Serie A")) -> 0.071193355 | M12: =IF(SUMIFS(Selections!$T$6:$T$27,Selections!$C$6:$C$27,"Serie A")=0,"n.a.",SUMIFS(Selections!$S$6:$S$27,Selections!$C$6:$C$27,"Serie A")/SUMIFS(Selections!$T$6:$T$27,Selections!$C$6:$C$27,"Serie A")) -> 0.73935409 | N12: =IF(SUMIFS(Selections!$T$6:$T$27,Selections!$C$6:$C$27,"Serie A")=0,"n.a.",(SUMIFS(Selections!$L$6:$L$27,Selections!$C$6:$C$27,"Serie A",Selections!$T$6:$T$27,1))/SUMIFS(Selections!$T$6:$T$27,Selections!$C$6:$C$27,"Serie A")) -> 1 | O12: =IF(SUMIFS(Selections!$T$6:$T$27,Selections!$C$6:$C$27,"Serie A")=0,"n.a.",(SUMIFS(Selections!$S$6:$S$27,Selections!$C$6:$C$27,"Serie A")-(SUMIFS(Selections!$L$6:$L$27,Selections!$C$6:$C$27,"Serie A",Selections!$T$6:$T$27,1)))/SUMIFS(Selections!$T$6:$T$27,Selections!$C$6:$C$27,"Serie A")) -> -0.26064591 | P12: =SUMIFS(Selections!$T$6:$T$27,Selections!$C$6:$C$27,"Serie A") -> 2 | Q12: =IF(P12<30,"Collect more scored forecasts (n="&P12&").",IF(O12>0.1,"Review overconfidence on a future holdout.",IF(K12<0,"Review prices and EV on a future holdout.","Continue forward testing. No automatic model change."))) -> Collect more scored forecasts (n=2).
A13: League | B13: UEFA Champions League | C13: =COUNTIFS(Selections!$C$6:$C$27,"UEFA Champions League") -> 5 | D13: =(COUNTIFS(Selections!$C$6:$C$27,"UEFA Champions League",Selections!$K$6:$K$27,"WON")+COUNTIFS(Selections!$C$6:$C$27,"UEFA Champions League",Selections!$K$6:$K$27,"LOST")) -> 4 | E13: =COUNTIFS(Selections!$C$6:$C$27,"UEFA Champions League",Selections!$K$6:$K$27,"WON") -> 4 | F13: =COUNTIFS(Selections!$C$6:$C$27,"UEFA Champions League",Selections!$K$6:$K$27,"LOST") -> 0 | G13: =COUNTIFS(Selections!$C$6:$C$27,"UEFA Champions League")-(COUNTIFS(Selections!$C$6:$C$27,"UEFA Champions League",Selections!$K$6:$K$27,"WON")+COUNTIFS(Selections!$C$6:$C$27,"UEFA Champions League",Selections!$K$6:$K$27,"LOST")) -> 1 | H13: =IF((COUNTIFS(Selections!$C$6:$C$27,"UEFA Champions League",Selections!$K$6:$K$27,"WON")+COUNTIFS(Selections!$C$6:$C$27,"UEFA Champions League",Selections!$K$6:$K$27,"LOST"))=0,"n.a.",COUNTIFS(Selections!$C$6:$C$27,"UEFA Champions League",Selections!$K$6:$K$27,"WON")/(COUNTIFS(Selections!$C$6:$C$27,"UEFA Champions League",Selections!$K$6:$K$27,"WON")+COUNTIFS(Selections!$C$6:$C$27,"UEFA Champions League",Selections!$K$6:$K$27,"LOST"))) -> 1 | I13: =SUMIFS(Selections!$M$6:$M$27,Selections!$C$6:$C$27,"UEFA Champions League") -> 4 | J13: =SUMIFS(Selections!$N$6:$N$27,Selections!$C$6:$C$27,"UEFA Champions League") -> 1.62 | K13: =IF(SUMIFS(Selections!$M$6:$M$27,Selections!$C$6:$C$27,"UEFA Champions League")=0,"n.a.",SUMIFS(Selections!$N$6:$N$27,Selections!$C$6:$C$27,"UEFA Champions League")/SUMIFS(Selections!$M$6:$M$27,Selections!$C$6:$C$27,"UEFA Champions League")) -> 0.405 | L13: =IF(SUMIFS(Selections!$T$6:$T$27,Selections!$C$6:$C$27,"UEFA Champions League")=0,"n.a.",SUMIFS(Selections!$O$6:$O$27,Selections!$C$6:$C$27,"UEFA Champions League")/SUMIFS(Selections!$T$6:$T$27,Selections!$C$6:$C$27,"UEFA Champions League")) -> 0.052539426 | M13: =IF(SUMIFS(Selections!$T$6:$T$27,Selections!$C$6:$C$27,"UEFA Champions League")=0,"n.a.",SUMIFS(Selections!$S$6:$S$27,Selections!$C$6:$C$27,"UEFA Champions League")/SUMIFS(Selections!$T$6:$T$27,Selections!$C$6:$C$27,"UEFA Champions League")) -> 0.80716344 | N13: =IF(SUMIFS(Selections!$T$6:$T$27,Selections!$C$6:$C$27,"UEFA Champions League")=0,"n.a.",(SUMIFS(Selections!$L$6:$L$27,Selections!$C$6:$C$27,"UEFA Champions League",Selections!$T$6:$T$27,1))/SUMIFS(Selections!$T$6:$T$27,Selections!$C$6:$C$27,"UEFA Champions League")) -> 1 | O13: =IF(SUMIFS(Selections!$T$6:$T$27,Selections!$C$6:$C$27,"UEFA Champions League")=0,"n.a.",(SUMIFS(Selections!$S$6:$S$27,Selections!$C$6:$C$27,"UEFA Champions League")-(SUMIFS(Selections!$L$6:$L$27,Selections!$C$6:$C$27,"UEFA Champions League",Selections!$T$6:$T$27,1)))/SUMIFS(Selections!$T$6:$T$27,Selections!$C$6:$C$27,"UEFA Champions League")) -> -0.19283656 | P13: =SUMIFS(Selections!$T$6:$T$27,Selections!$C$6:$C$27,"UEFA Champions League") -> 4 | Q13: =IF(P13<30,"Collect more scored forecasts (n="&P13&").",IF(O13>0.1,"Review overconfidence on a future holdout.",IF(K13<0,"Review prices and EV on a future holdout.","Continue forward testing. No automatic model change."))) -> Collect more scored forecasts (n=4).
A14: Market | B14: Away win | C14: =COUNTIFS(Selections!$E$6:$E$27,"Away win") -> 1 | D14: =(COUNTIFS(Selections!$E$6:$E$27,"Away win",Selections!$K$6:$K$27,"WON")+COUNTIFS(Selections!$E$6:$E$27,"Away win",Selections!$K$6:$K$27,"LOST")) -> 0 | E14: =COUNTIFS(Selections!$E$6:$E$27,"Away win",Selections!$K$6:$K$27,"WON") -> 0 | F14: =COUNTIFS(Selections!$E$6:$E$27,"Away win",Selections!$K$6:$K$27,"LOST") -> 0 | G14: =COUNTIFS(Selections!$E$6:$E$27,"Away win")-(COUNTIFS(Selections!$E$6:$E$27,"Away win",Selections!$K$6:$K$27,"WON")+COUNTIFS(Selections!$E$6:$E$27,"Away win",Selections!$K$6:$K$27,"LOST")) -> 1 | H14: =IF((COUNTIFS(Selections!$E$6:$E$27,"Away win",Selections!$K$6:$K$27,"WON")+COUNTIFS(Selections!$E$6:$E$27,"Away win",Selections!$K$6:$K$27,"LOST"))=0,"n.a.",COUNTIFS(Selections!$E$6:$E$27,"Away win",Selections!$K$6:$K$27,"WON")/(COUNTIFS(Selections!$E$6:$E$27,"Away win",Selections!$K$6:$K$27,"WON")+COUNTIFS(Selections!$E$6:$E$27,"Away win",Selections!$K$6:$K$27,"LOST"))) -> n.a. | I14: =SUMIFS(Selections!$M$6:$M$27,Selections!$E$6:$E$27,"Away win") -> 0 | J14: =SUMIFS(Selections!$N$6:$N$27,Selections!$E$6:$E$27,"Away win") -> 0 | K14: =IF(SUMIFS(Selections!$M$6:$M$27,Selections!$E$6:$E$27,"Away win")=0,"n.a.",SUMIFS(Selections!$N$6:$N$27,Selections!$E$6:$E$27,"Away win")/SUMIFS(Selections!$M$6:$M$27,Selections!$E$6:$E$27,"Away win")) -> n.a. | L14: =IF(SUMIFS(Selections!$T$6:$T$27,Selections!$E$6:$E$27,"Away win")=0,"n.a.",SUMIFS(Selections!$O$6:$O$27,Selections!$E$6:$E$27,"Away win")/SUMIFS(Selections!$T$6:$T$27,Selections!$E$6:$E$27,"Away win")) -> n.a. | M14: =IF(SUMIFS(Selections!$T$6:$T$27,Selections!$E$6:$E$27,"Away win")=0,"n.a.",SUMIFS(Selections!$S$6:$S$27,Selections!$E$6:$E$27,"Away win")/SUMIFS(Selections!$T$6:$T$27,Selections!$E$6:$E$27,"Away win")) -> n.a. | N14: =IF(SUMIFS(Selections!$T$6:$T$27,Selections!$E$6:$E$27,"Away win")=0,"n.a.",(SUMIFS(Selections!$L$6:$L$27,Selections!$E$6:$E$27,"Away win",Selections!$T$6:$T$27,1))/SUMIFS(Selections!$T$6:$T$27,Selections!$E$6:$E$27,"Away win")) -> n.a. | O14: =IF(SUMIFS(Selections!$T$6:$T$27,Selections!$E$6:$E$27,"Away win")=0,"n.a.",(SUMIFS(Selections!$S$6:$S$27,Selections!$E$6:$E$27,"Away win")-(SUMIFS(Selections!$L$6:$L$27,Selections!$E$6:$E$27,"Away win",Selections!$T$6:$T$27,1)))/SUMIFS(Selections!$T$6:$T$27,Selections!$E$6:$E$27,"Away win")) -> n.a. | P14: =SUMIFS(Selections!$T$6:$T$27,Selections!$E$6:$E$27,"Away win") -> 0 | Q14: =IF(P14<30,"Collect more scored forecasts (n="&P14&").",IF(O14>0.1,"Review overconfidence on a future holdout.",IF(K14<0,"Review prices and EV on a future holdout.","Continue forward testing. No automatic model change."))) -> Collect more scored forecasts (n=0).
A15: Market | B15: Both Teams to Score - Yes | C15: =COUNTIFS(Selections!$E$6:$E$27,"Both Teams to Score - Yes") -> 1 | D15: =(COUNTIFS(Selections!$E$6:$E$27,"Both Teams to Score - Yes",Selections!$K$6:$K$27,"WON")+COUNTIFS(Selections!$E$6:$E$27,"Both Teams to Score - Yes",Selections!$K$6:$K$27,"LOST")) -> 1 | E15: =COUNTIFS(Selections!$E$6:$E$27,"Both Teams to Score - Yes",Selections!$K$6:$K$27,"WON") -> 1 | F15: =COUNTIFS(Selections!$E$6:$E$27,"Both Teams to Score - Yes",Selections!$K$6:$K$27,"LOST") -> 0 | G15: =COUNTIFS(Selections!$E$6:$E$27,"Both Teams to Score - Yes")-(COUNTIFS(Selections!$E$6:$E$27,"Both Teams to Score - Yes",Selections!$K$6:$K$27,"WON")+COUNTIFS(Selections!$E$6:$E$27,"Both Teams to Score - Yes",Selections!$K$6:$K$27,"LOST")) -> 0 | H15: =IF((COUNTIFS(Selections!$E$6:$E$27,"Both Teams to Score - Yes",Selections!$K$6:$K$27,"WON")+COUNTIFS(Selections!$E$6:$E$27,"Both Teams to Score - Yes",Selections!$K$6:$K$27,"LOST"))=0,"n.a.",COUNTIFS(Selections!$E$6:$E$27,"Both Teams to Score - Yes",Selections!$K$6:$K$27,"WON")/(COUNTIFS(Selections!$E$6:$E$27,"Both Teams to Score - Yes",Selections!$K$6:$K$27,"WON")+COUNTIFS(Selections!$E$6:$E$27,"Both Teams to Score - Yes",Selections!$K$6:$K$27,"LOST"))) -> 1 | I15: =SUMIFS(Selections!$M$6:$M$27,Selections!$E$6:$E$27,"Both Teams to Score - Yes") -> 1 | J15: =SUMIFS(Selections!$N$6:$N$27,Selections!$E$6:$E$27,"Both Teams to Score - Yes") -> 0.49 | K15: =IF(SUMIFS(Selections!$M$6:$M$27,Selections!$E$6:$E$27,"Both Teams to Score - Yes")=0,"n.a.",SUMIFS(Selections!$N$6:$N$27,Selections!$E$6:$E$27,"Both Teams to Score - Yes")/SUMIFS(Selections!$M$6:$M$27,Selections!$E$6:$E$27,"Both Teams to Score - Yes")) -> 0.49 | L15: =IF(SUMIFS(Selections!$T$6:$T$27,Selections!$E$6:$E$27,"Both Teams to Score - Yes")=0,"n.a.",SUMIFS(Selections!$O$6:$O$27,Selections!$E$6:$E$27,"Both Teams to Score - Yes")/SUMIFS(Selections!$T$6:$T$27,Selections!$E$6:$E$27,"Both Teams to Score - Yes")) -> 0.086628456 | M15: =IF(SUMIFS(Selections!$T$6:$T$27,Selections!$E$6:$E$27,"Both Teams to Score - Yes")=0,"n.a.",SUMIFS(Selections!$S$6:$S$27,Selections!$E$6:$E$27,"Both Teams to Score - Yes")/SUMIFS(Selections!$T$6:$T$27,Selections!$E$6:$E$27,"Both Teams to Score - Yes")) -> 0.70567288 | N15: =IF(SUMIFS(Selections!$T$6:$T$27,Selections!$E$6:$E$27,"Both Teams to Score - Yes")=0,"n.a.",(SUMIFS(Selections!$L$6:$L$27,Selections!$E$6:$E$27,"Both Teams to Score - Yes",Selections!$T$6:$T$27,1))/SUMIFS(Selections!$T$6:$T$27,Selections!$E$6:$E$27,"Both Teams to Score - Yes")) -> 1 | O15: =IF(SUMIFS(Selections!$T$6:$T$27,Selections!$E$6:$E$27,"Both Teams to Score - Yes")=0,"n.a.",(SUMIFS(Selections!$S$6:$S$27,Selections!$E$6:$E$27,"Both Teams to Score - Yes")-(SUMIFS(Selections!$L$6:$L$27,Selections!$E$6:$E$27,"Both Teams to Score - Yes",Selections!$T$6:$T$27,1)))/SUMIFS(Selections!$T$6:$T$27,Selections!$E$6:$E$27,"Both Teams to Score - Yes")) -> -0.29432712 | P15: =SUMIFS(Selections!$T$6:$T$27,Selections!$E$6:$E$27,"Both Teams to Score - Yes") -> 1 | Q15: =IF(P15<30,"Collect more scored forecasts (n="&P15&").",IF(O15>0.1,"Review overconfidence on a future holdout.",IF(K15<0,"Review prices and EV on a future holdout.","Continue forward testing. No automatic model change."))) -> Collect more scored forecasts (n=1).
A16: Market | B16: Double Chance 1X | C16: =COUNTIFS(Selections!$E$6:$E$27,"Double Chance 1X") -> 1 | D16: =(COUNTIFS(Selections!$E$6:$E$27,"Double Chance 1X",Selections!$K$6:$K$27,"WON")+COUNTIFS(Selections!$E$6:$E$27,"Double Chance 1X",Selections!$K$6:$K$27,"LOST")) -> 0 | E16: =COUNTIFS(Selections!$E$6:$E$27,"Double Chance 1X",Selections!$K$6:$K$27,"WON") -> 0 | F16: =COUNTIFS(Selections!$E$6:$E$27,"Double Chance 1X",Selections!$K$6:$K$27,"LOST") -> 0 | G16: =COUNTIFS(Selections!$E$6:$E$27,"Double Chance 1X")-(COUNTIFS(Selections!$E$6:$E$27,"Double Chance 1X",Selections!$K$6:$K$27,"WON")+COUNTIFS(Selections!$E$6:$E$27,"Double Chance 1X",Selections!$K$6:$K$27,"LOST")) -> 1 | H16: =IF((COUNTIFS(Selections!$E$6:$E$27,"Double Chance 1X",Selections!$K$6:$K$27,"WON")+COUNTIFS(Selections!$E$6:$E$27,"Double Chance 1X",Selections!$K$6:$K$27,"LOST"))=0,"n.a.",COUNTIFS(Selections!$E$6:$E$27,"Double Chance 1X",Selections!$K$6:$K$27,"WON")/(COUNTIFS(Selections!$E$6:$E$27,"Double Chance 1X",Selections!$K$6:$K$27,"WON")+COUNTIFS(Selections!$E$6:$E$27,"Double Chance 1X",Selections!$K$6:$K$27,"LOST"))) -> n.a. | I16: =SUMIFS(Selections!$M$6:$M$27,Selections!$E$6:$E$27,"Double Chance 1X") -> 0 | J16: =SUMIFS(Selections!$N$6:$N$27,Selections!$E$6:$E$27,"Double Chance 1X") -> 0 | K16: =IF(SUMIFS(Selections!$M$6:$M$27,Selections!$E$6:$E$27,"Double Chance 1X")=0,"n.a.",SUMIFS(Selections!$N$6:$N$27,Selections!$E$6:$E$27,"Double Chance 1X")/SUMIFS(Selections!$M$6:$M$27,Selections!$E$6:$E$27,"Double Chance 1X")) -> n.a. | L16: =IF(SUMIFS(Selections!$T$6:$T$27,Selections!$E$6:$E$27,"Double Chance 1X")=0,"n.a.",SUMIFS(Selections!$O$6:$O$27,Selections!$E$6:$E$27,"Double Chance 1X")/SUMIFS(Selections!$T$6:$T$27,Selections!$E$6:$E$27,"Double Chance 1X")) -> n.a. | M16: =IF(SUMIFS(Selections!$T$6:$T$27,Selections!$E$6:$E$27,"Double Chance 1X")=0,"n.a.",SUMIFS(Selections!$S$6:$S$27,Selections!$E$6:$E$27,"Double Chance 1X")/SUMIFS(Selections!$T$6:$T$27,Selections!$E$6:$E$27,"Double Chance 1X")) -> n.a. | N16: =IF(SUMIFS(Selections!$T$6:$T$27,Selections!$E$6:$E$27,"Double Chance 1X")=0,"n.a.",(SUMIFS(Selections!$L$6:$L$27,Selections!$E$6:$E$27,"Double Chance 1X",Selections!$T$6:$T$27,1))/SUMIFS(Selections!$T$6:$T$27,Selections!$E$6:$E$27,"Double Chance 1X")) -> n.a. | O16: =IF(SUMIFS(Selections!$T$6:$T$27,Selections!$E$6:$E$27,"Double Chance 1X")=0,"n.a.",(SUMIFS(Selections!$S$6:$S$27,Selections!$E$6:$E$27,"Double Chance 1X")-(SUMIFS(Selections!$L$6:$L$27,Selections!$E$6:$E$27,"Double Chance 1X",Selections!$T$6:$T$27,1)))/SUMIFS(Selections!$T$6:$T$27,Selections!$E$6:$E$27,"Double Chance 1X")) -> n.a. | P16: =SUMIFS(Selections!$T$6:$T$27,Selections!$E$6:$E$27,"Double Chance 1X") -> 0 | Q16: =IF(P16<30,"Collect more scored forecasts (n="&P16&").",IF(O16>0.1,"Review overconfidence on a future holdout.",IF(K16<0,"Review prices and EV on a future holdout.","Continue forward testing. No automatic model change."))) -> Collect more scored forecasts (n=0).
A17: Market | B17: Home win | C17: =COUNTIFS(Selections!$E$6:$E$27,"Home win") -> 4 | D17: =(COUNTIFS(Selections!$E$6:$E$27,"Home win",Selections!$K$6:$K$27,"WON")+COUNTIFS(Selections!$E$6:$E$27,"Home win",Selections!$K$6:$K$27,"LOST")) -> 2 | E17: =COUNTIFS(Selections!$E$6:$E$27,"Home win",Selections!$K$6:$K$27,"WON") -> 2 | F17: =COUNTIFS(Selections!$E$6:$E$27,"Home win",Selections!$K$6:$K$27,"LOST") -> 0 | G17: =COUNTIFS(Selections!$E$6:$E$27,"Home win")-(COUNTIFS(Selections!$E$6:$E$27,"Home win",Selections!$K$6:$K$27,"WON")+COUNTIFS(Selections!$E$6:$E$27,"Home win",Selections!$K$6:$K$27,"LOST")) -> 2 | H17: =IF((COUNTIFS(Selections!$E$6:$E$27,"Home win",Selections!$K$6:$K$27,"WON")+COUNTIFS(Selections!$E$6:$E$27,"Home win",Selections!$K$6:$K$27,"LOST"))=0,"n.a.",COUNTIFS(Selections!$E$6:$E$27,"Home win",Selections!$K$6:$K$27,"WON")/(COUNTIFS(Selections!$E$6:$E$27,"Home win",Selections!$K$6:$K$27,"WON")+COUNTIFS(Selections!$E$6:$E$27,"Home win",Selections!$K$6:$K$27,"LOST"))) -> 1 | I17: =SUMIFS(Selections!$M$6:$M$27,Selections!$E$6:$E$27,"Home win") -> 2 | J17: =SUMIFS(Selections!$N$6:$N$27,Selections!$E$6:$E$27,"Home win") -> 1.37 | K17: =IF(SUMIFS(Selections!$M$6:$M$27,Selections!$E$6:$E$27,"Home win")=0,"n.a.",SUMIFS(Selections!$N$6:$N$27,Selections!$E$6:$E$27,"Home win")/SUMIFS(Selections!$M$6:$M$27,Selections!$E$6:$E$27,"Home win")) -> 0.685 | L17: =IF(SUMIFS(Selections!$T$6:$T$27,Selections!$E$6:$E$27,"Home win")=0,"n.a.",SUMIFS(Selections!$O$6:$O$27,Selections!$E$6:$E$27,"Home win")/SUMIFS(Selections!$T$6:$T$27,Selections!$E$6:$E$27,"Home win")) -> 0.10707454 | M17: =IF(SUMIFS(Selections!$T$6:$T$27,Selections!$E$6:$E$27,"Home win")=0,"n.a.",SUMIFS(Selections!$S$6:$S$27,Selections!$E$6:$E$27,"Home win")/SUMIFS(Selections!$T$6:$T$27,Selections!$E$6:$E$27,"Home win")) -> 0.67291177 | N17: =IF(SUMIFS(Selections!$T$6:$T$27,Selections!$E$6:$E$27,"Home win")=0,"n.a.",(SUMIFS(Selections!$L$6:$L$27,Selections!$E$6:$E$27,"Home win",Selections!$T$6:$T$27,1))/SUMIFS(Selections!$T$6:$T$27,Selections!$E$6:$E$27,"Home win")) -> 1 | O17: =IF(SUMIFS(Selections!$T$6:$T$27,Selections!$E$6:$E$27,"Home win")=0,"n.a.",(SUMIFS(Selections!$S$6:$S$27,Selections!$E$6:$E$27,"Home win")-(SUMIFS(Selections!$L$6:$L$27,Selections!$E$6:$E$27,"Home win",Selections!$T$6:$T$27,1)))/SUMIFS(Selections!$T$6:$T$27,Selections!$E$6:$E$27,"Home win")) -> -0.32708823 | P17: =SUMIFS(Selections!$T$6:$T$27,Selections!$E$6:$E$27,"Home win") -> 2 | Q17: =IF(P17<30,"Collect more scored forecasts (n="&P17&").",IF(O17>0.1,"Review overconfidence on a future holdout.",IF(K17<0,"Review prices and EV on a future holdout.","Continue forward testing. No automatic model change."))) -> Collect more scored forecasts (n=2).
A18: Market | B18: Over 1.5 | C18: =COUNTIFS(Selections!$E$6:$E$27,"Over 1.5") -> 9 | D18: =(COUNTIFS(Selections!$E$6:$E$27,"Over 1.5",Selections!$K$6:$K$27,"WON")+COUNTIFS(Selections!$E$6:$E$27,"Over 1.5",Selections!$K$6:$K$27,"LOST")) -> 4 | E18: =COUNTIFS(Selections!$E$6:$E$27,"Over 1.5",Selections!$K$6:$K$27,"WON") -> 4 | F18: =COUNTIFS(Selections!$E$6:$E$27,"Over 1.5",Selections!$K$6:$K$27,"LOST") -> 0 | G18: =COUNTIFS(Selections!$E$6:$E$27,"Over 1.5")-(COUNTIFS(Selections!$E$6:$E$27,"Over 1.5",Selections!$K$6:$K$27,"WON")+COUNTIFS(Selections!$E$6:$E$27,"Over 1.5",Selections!$K$6:$K$27,"LOST")) -> 5 | H18: =IF((COUNTIFS(Selections!$E$6:$E$27,"Over 1.5",Selections!$K$6:$K$27,"WON")+COUNTIFS(Selections!$E$6:$E$27,"Over 1.5",Selections!$K$6:$K$27,"LOST"))=0,"n.a.",COUNTIFS(Selections!$E$6:$E$27,"Over 1.5",Selections!$K$6:$K$27,"WON")/(COUNTIFS(Selections!$E$6:$E$27,"Over 1.5",Selections!$K$6:$K$27,"WON")+COUNTIFS(Selections!$E$6:$E$27,"Over 1.5",Selections!$K$6:$K$27,"LOST"))) -> 1 | I18: =SUMIFS(Selections!$M$6:$M$27,Selections!$E$6:$E$27,"Over 1.5") -> 4 | J18: =SUMIFS(Selections!$N$6:$N$27,Selections!$E$6:$E$27,"Over 1.5") -> 0.97 | K18: =IF(SUMIFS(Selections!$M$6:$M$27,Selections!$E$6:$E$27,"Over 1.5")=0,"n.a.",SUMIFS(Selections!$N$6:$N$27,Selections!$E$6:$E$27,"Over 1.5")/SUMIFS(Selections!$M$6:$M$27,Selections!$E$6:$E$27,"Over 1.5")) -> 0.2425 | L18: =IF(SUMIFS(Selections!$T$6:$T$27,Selections!$E$6:$E$27,"Over 1.5")=0,"n.a.",SUMIFS(Selections!$O$6:$O$27,Selections!$E$6:$E$27,"Over 1.5")/SUMIFS(Selections!$T$6:$T$27,Selections!$E$6:$E$27,"Over 1.5")) -> 0.016985304 | M18: =IF(SUMIFS(Selections!$T$6:$T$27,Selections!$E$6:$E$27,"Over 1.5")=0,"n.a.",SUMIFS(Selections!$S$6:$S$27,Selections!$E$6:$E$27,"Over 1.5")/SUMIFS(Selections!$T$6:$T$27,Selections!$E$6:$E$27,"Over 1.5")) -> 0.88524571 | N18: =IF(SUMIFS(Selections!$T$6:$T$27,Selections!$E$6:$E$27,"Over 1.5")=0,"n.a.",(SUMIFS(Selections!$L$6:$L$27,Selections!$E$6:$E$27,"Over 1.5",Selections!$T$6:$T$27,1))/SUMIFS(Selections!$T$6:$T$27,Selections!$E$6:$E$27,"Over 1.5")) -> 1 | O18: =IF(SUMIFS(Selections!$T$6:$T$27,Selections!$E$6:$E$27,"Over 1.5")=0,"n.a.",(SUMIFS(Selections!$S$6:$S$27,Selections!$E$6:$E$27,"Over 1.5")-(SUMIFS(Selections!$L$6:$L$27,Selections!$E$6:$E$27,"Over 1.5",Selections!$T$6:$T$27,1)))/SUMIFS(Selections!$T$6:$T$27,Selections!$E$6:$E$27,"Over 1.5")) -> -0.11475429 | P18: =SUMIFS(Selections!$T$6:$T$27,Selections!$E$6:$E$27,"Over 1.5") -> 4 | Q18: =IF(P18<30,"Collect more scored forecasts (n="&P18&").",IF(O18>0.1,"Review overconfidence on a future holdout.",IF(K18<0,"Review prices and EV on a future holdout.","Continue forward testing. No automatic model change."))) -> Collect more scored forecasts (n=4).
A19: Market | B19: Under 3.5 | C19: =COUNTIFS(Selections!$E$6:$E$27,"Under 3.5") -> 6 | D19: =(COUNTIFS(Selections!$E$6:$E$27,"Under 3.5",Selections!$K$6:$K$27,"WON")+COUNTIFS(Selections!$E$6:$E$27,"Under 3.5",Selections!$K$6:$K$27,"LOST")) -> 4 | E19: =COUNTIFS(Selections!$E$6:$E$27,"Under 3.5",Selections!$K$6:$K$27,"WON") -> 1 | F19: =COUNTIFS(Selections!$E$6:$E$27,"Under 3.5",Selections!$K$6:$K$27,"LOST") -> 3 | G19: =COUNTIFS(Selections!$E$6:$E$27,"Under 3.5")-(COUNTIFS(Selections!$E$6:$E$27,"Under 3.5",Selections!$K$6:$K$27,"WON")+COUNTIFS(Selections!$E$6:$E$27,"Under 3.5",Selections!$K$6:$K$27,"LOST")) -> 2 | H19: =IF((COUNTIFS(Selections!$E$6:$E$27,"Under 3.5",Selections!$K$6:$K$27,"WON")+COUNTIFS(Selections!$E$6:$E$27,"Under 3.5",Selections!$K$6:$K$27,"LOST"))=0,"n.a.",COUNTIFS(Selections!$E$6:$E$27,"Under 3.5",Selections!$K$6:$K$27,"WON")/(COUNTIFS(Selections!$E$6:$E$27,"Under 3.5",Selections!$K$6:$K$27,"WON")+COUNTIFS(Selections!$E$6:$E$27,"Under 3.5",Selections!$K$6:$K$27,"LOST"))) -> 0.25 | I19: =SUMIFS(Selections!$M$6:$M$27,Selections!$E$6:$E$27,"Under 3.5") -> 4 | J19: =SUMIFS(Selections!$N$6:$N$27,Selections!$E$6:$E$27,"Under 3.5") -> -2.72 | K19: =IF(SUMIFS(Selections!$M$6:$M$27,Selections!$E$6:$E$27,"Under 3.5")=0,"n.a.",SUMIFS(Selections!$N$6:$N$27,Selections!$E$6:$E$27,"Under 3.5")/SUMIFS(Selections!$M$6:$M$27,Selections!$E$6:$E$27,"Under 3.5")) -> -0.68 | L19: =IF(SUMIFS(Selections!$T$6:$T$27,Selections!$E$6:$E$27,"Under 3.5")=0,"n.a.",SUMIFS(Selections!$O$6:$O$27,Selections!$E$6:$E$27,"Under 3.5")/SUMIFS(Selections!$T$6:$T$27,Selections!$E$6:$E$27,"Under 3.5")) -> 0.50163322 | M19: =IF(SUMIFS(Selections!$T$6:$T$27,Selections!$E$6:$E$27,"Under 3.5")=0,"n.a.",SUMIFS(Selections!$S$6:$S$27,Selections!$E$6:$E$27,"Under 3.5")/SUMIFS(Selections!$T$6:$T$27,Selections!$E$6:$E$27,"Under 3.5")) -> 0.80545037 | N19: =IF(SUMIFS(Selections!$T$6:$T$27,Selections!$E$6:$E$27,"Under 3.5")=0,"n.a.",(SUMIFS(Selections!$L$6:$L$27,Selections!$E$6:$E$27,"Under 3.5",Selections!$T$6:$T$27,1))/SUMIFS(Selections!$T$6:$T$27,Selections!$E$6:$E$27,"Under 3.5")) -> 0.25 | O19: =IF(SUMIFS(Selections!$T$6:$T$27,Selections!$E$6:$E$27,"Under 3.5")=0,"n.a.",(SUMIFS(Selections!$S$6:$S$27,Selections!$E$6:$E$27,"Under 3.5")-(SUMIFS(Selections!$L$6:$L$27,Selections!$E$6:$E$27,"Under 3.5",Selections!$T$6:$T$27,1)))/SUMIFS(Selections!$T$6:$T$27,Selections!$E$6:$E$27,"Under 3.5")) -> 0.55545037 | P19: =SUMIFS(Selections!$T$6:$T$27,Selections!$E$6:$E$27,"Under 3.5") -> 4 | Q19: =IF(P19<30,"Collect more scored forecasts (n="&P19&").",IF(O19>0.1,"Review overconfidence on a future holdout.",IF(K19<0,"Review prices and EV on a future holdout.","Continue forward testing. No automatic model change."))) -> Collect more scored forecasts (n=4).
A20: Policy | B20: 72h-all-markets-net-ev15-execution-v7 | C20: =COUNTIFS(Selections!$G$6:$G$27,"72h-all-markets-net-ev15-execution-v7") -> 2 | D20: =(COUNTIFS(Selections!$G$6:$G$27,"72h-all-markets-net-ev15-execution-v7",Selections!$K$6:$K$27,"WON")+COUNTIFS(Selections!$G$6:$G$27,"72h-all-markets-net-ev15-execution-v7",Selections!$K$6:$K$27,"LOST")) -> 0 | E20: =COUNTIFS(Selections!$G$6:$G$27,"72h-all-markets-net-ev15-execution-v7",Selections!$K$6:$K$27,"WON") -> 0 | F20: =COUNTIFS(Selections!$G$6:$G$27,"72h-all-markets-net-ev15-execution-v7",Selections!$K$6:$K$27,"LOST") -> 0 | G20: =COUNTIFS(Selections!$G$6:$G$27,"72h-all-markets-net-ev15-execution-v7")-(COUNTIFS(Selections!$G$6:$G$27,"72h-all-markets-net-ev15-execution-v7",Selections!$K$6:$K$27,"WON")+COUNTIFS(Selections!$G$6:$G$27,"72h-all-markets-net-ev15-execution-v7",Selections!$K$6:$K$27,"LOST")) -> 2 | H20: =IF((COUNTIFS(Selections!$G$6:$G$27,"72h-all-markets-net-ev15-execution-v7",Selections!$K$6:$K$27,"WON")+COUNTIFS(Selections!$G$6:$G$27,"72h-all-markets-net-ev15-execution-v7",Selections!$K$6:$K$27,"LOST"))=0,"n.a.",COUNTIFS(Selections!$G$6:$G$27,"72h-all-markets-net-ev15-execution-v7",Selections!$K$6:$K$27,"WON")/(COUNTIFS(Selections!$G$6:$G$27,"72h-all-markets-net-ev15-execution-v7",Selections!$K$6:$K$27,"WON")+COUNTIFS(Selections!$G$6:$G$27,"72h-all-markets-net-ev15-execution-v7",Selections!$K$6:$K$27,"LOST"))) -> n.a. | I20: =SUMIFS(Selections!$M$6:$M$27,Selections!$G$6:$G$27,"72h-all-markets-net-ev15-execution-v7") -> 0 | J20: =SUMIFS(Selections!$N$6:$N$27,Selections!$G$6:$G$27,"72h-all-markets-net-ev15-execution-v7") -> 0 | K20: =IF(SUMIFS(Selections!$M$6:$M$27,Selections!$G$6:$G$27,"72h-all-markets-net-ev15-execution-v7")=0,"n.a.",SUMIFS(Selections!$N$6:$N$27,Selections!$G$6:$G$27,"72h-all-markets-net-ev15-execution-v7")/SUMIFS(Selections!$M$6:$M$27,Selections!$G$6:$G$27,"72h-all-markets-net-ev15-execution-v7")) -> n.a. | L20: =IF(SUMIFS(Selections!$T$6:$T$27,Selections!$G$6:$G$27,"72h-all-markets-net-ev15-execution-v7")=0,"n.a.",SUMIFS(Selections!$O$6:$O$27,Selections!$G$6:$G$27,"72h-all-markets-net-ev15-execution-v7")/SUMIFS(Selections!$T$6:$T$27,Selections!$G$6:$G$27,"72h-all-markets-net-ev15-execution-v7")) -> n.a. | M20: =IF(SUMIFS(Selections!$T$6:$T$27,Selections!$G$6:$G$27,"72h-all-markets-net-ev15-execution-v7")=0,"n.a.",SUMIFS(Selections!$S$6:$S$27,Selections!$G$6:$G$27,"72h-all-markets-net-ev15-execution-v7")/SUMIFS(Selections!$T$6:$T$27,Selections!$G$6:$G$27,"72h-all-markets-net-ev15-execution-v7")) -> n.a. | N20: =IF(SUMIFS(Selections!$T$6:$T$27,Selections!$G$6:$G$27,"72h-all-markets-net-ev15-execution-v7")=0,"n.a.",(SUMIFS(Selections!$L$6:$L$27,Selections!$G$6:$G$27,"72h-all-markets-net-ev15-execution-v7",Selections!$T$6:$T$27,1))/SUMIFS(Selections!$T$6:$T$27,Selections!$G$6:$G$27,"72h-all-markets-net-ev15-execution-v7")) -> n.a. | O20: =IF(SUMIFS(Selections!$T$6:$T$27,Selections!$G$6:$G$27,"72h-all-markets-net-ev15-execution-v7")=0,"n.a.",(SUMIFS(Selections!$S$6:$S$27,Selections!$G$6:$G$27,"72h-all-markets-net-ev15-execution-v7")-(SUMIFS(Selections!$L$6:$L$27,Selections!$G$6:$G$27,"72h-all-markets-net-ev15-execution-v7",Selections!$T$6:$T$27,1)))/SUMIFS(Selections!$T$6:$T$27,Selections!$G$6:$G$27,"72h-all-markets-net-ev15-execution-v7")) -> n.a. | P20: =SUMIFS(Selections!$T$6:$T$27,Selections!$G$6:$G$27,"72h-all-markets-net-ev15-execution-v7") -> 0 | Q20: =IF(P20<30,"Collect more scored forecasts (n="&P20&").",IF(O20>0.1,"Review overconfidence on a future holdout.",IF(K20<0,"Review prices and EV on a future holdout.","Continue forward testing. No automatic model change."))) -> Collect more scored forecasts (n=0).
A21: Policy | B21: 72h-six-markets-dc12-probability-odds-net-ev15-v9 | C21: =COUNTIFS(Selections!$G$6:$G$27,"72h-six-markets-dc12-probability-odds-net-ev15-v9") -> 1 | D21: =(COUNTIFS(Selections!$G$6:$G$27,"72h-six-markets-dc12-probability-odds-net-ev15-v9",Selections!$K$6:$K$27,"WON")+COUNTIFS(Selections!$G$6:$G$27,"72h-six-markets-dc12-probability-odds-net-ev15-v9",Selections!$K$6:$K$27,"LOST")) -> 0 | E21: =COUNTIFS(Selections!$G$6:$G$27,"72h-six-markets-dc12-probability-odds-net-ev15-v9",Selections!$K$6:$K$27,"WON") -> 0 | F21: =COUNTIFS(Selections!$G$6:$G$27,"72h-six-markets-dc12-probability-odds-net-ev15-v9",Selections!$K$6:$K$27,"LOST") -> 0 | G21: =COUNTIFS(Selections!$G$6:$G$27,"72h-six-markets-dc12-probability-odds-net-ev15-v9")-(COUNTIFS(Selections!$G$6:$G$27,"72h-six-markets-dc12-probability-odds-net-ev15-v9",Selections!$K$6:$K$27,"WON")+COUNTIFS(Selections!$G$6:$G$27,"72h-six-markets-dc12-probability-odds-net-ev15-v9",Selections!$K$6:$K$27,"LOST")) -> 1 | H21: =IF((COUNTIFS(Selections!$G$6:$G$27,"72h-six-markets-dc12-probability-odds-net-ev15-v9",Selections!$K$6:$K$27,"WON")+COUNTIFS(Selections!$G$6:$G$27,"72h-six-markets-dc12-probability-odds-net-ev15-v9",Selections!$K$6:$K$27,"LOST"))=0,"n.a.",COUNTIFS(Selections!$G$6:$G$27,"72h-six-markets-dc12-probability-odds-net-ev15-v9",Selections!$K$6:$K$27,"WON")/(COUNTIFS(Selections!$G$6:$G$27,"72h-six-markets-dc12-probability-odds-net-ev15-v9",Selections!$K$6:$K$27,"WON")+COUNTIFS(Selections!$G$6:$G$27,"72h-six-markets-dc12-probability-odds-net-ev15-v9",Selections!$K$6:$K$27,"LOST"))) -> n.a. | I21: =SUMIFS(Selections!$M$6:$M$27,Selections!$G$6:$G$27,"72h-six-markets-dc12-probability-odds-net-ev15-v9") -> 0 | J21: =SUMIFS(Selections!$N$6:$N$27,Selections!$G$6:$G$27,"72h-six-markets-dc12-probability-odds-net-ev15-v9") -> 0 | K21: =IF(SUMIFS(Selections!$M$6:$M$27,Selections!$G$6:$G$27,"72h-six-markets-dc12-probability-odds-net-ev15-v9")=0,"n.a.",SUMIFS(Selections!$N$6:$N$27,Selections!$G$6:$G$27,"72h-six-markets-dc12-probability-odds-net-ev15-v9")/SUMIFS(Selections!$M$6:$M$27,Selections!$G$6:$G$27,"72h-six-markets-dc12-probability-odds-net-ev15-v9")) -> n.a. | L21: =IF(SUMIFS(Selections!$T$6:$T$27,Selections!$G$6:$G$27,"72h-six-markets-dc12-probability-odds-net-ev15-v9")=0,"n.a.",SUMIFS(Selections!$O$6:$O$27,Selections!$G$6:$G$27,"72h-six-markets-dc12-probability-odds-net-ev15-v9")/SUMIFS(Selections!$T$6:$T$27,Selections!$G$6:$G$27,"72h-six-markets-dc12-probability-odds-net-ev15-v9")) -> n.a. | M21: =IF(SUMIFS(Selections!$T$6:$T$27,Selections!$G$6:$G$27,"72h-six-markets-dc12-probability-odds-net-ev15-v9")=0,"n.a.",SUMIFS(Selections!$S$6:$S$27,Selections!$G$6:$G$27,"72h-six-markets-dc12-probability-odds-net-ev15-v9")/SUMIFS(Selections!$T$6:$T$27,Selections!$G$6:$G$27,"72h-six-markets-dc12-probability-odds-net-ev15-v9")) -> n.a. | N21: =IF(SUMIFS(Selections!$T$6:$T$27,Selections!$G$6:$G$27,"72h-six-markets-dc12-probability-odds-net-ev15-v9")=0,"n.a.",(SUMIFS(Selections!$L$6:$L$27,Selections!$G$6:$G$27,"72h-six-markets-dc12-probability-odds-net-ev15-v9",Selections!$T$6:$T$27,1))/SUMIFS(Selections!$T$6:$T$27,Selections!$G$6:$G$27,"72h-six-markets-dc12-probability-odds-net-ev15-v9")) -> n.a. | O21: =IF(SUMIFS(Selections!$T$6:$T$27,Selections!$G$6:$G$27,"72h-six-markets-dc12-probability-odds-net-ev15-v9")=0,"n.a.",(SUMIFS(Selections!$S$6:$S$27,Selections!$G$6:$G$27,"72h-six-markets-dc12-probability-odds-net-ev15-v9")-(SUMIFS(Selections!$L$6:$L$27,Selections!$G$6:$G$27,"72h-six-markets-dc12-probability-odds-net-ev15-v9",Selections!$T$6:$T$27,1)))/SUMIFS(Selections!$T$6:$T$27,Selections!$G$6:$G$27,"72h-six-markets-dc12-probability-odds-net-ev15-v9")) -> n.a. | P21: =SUMIFS(Selections!$T$6:$T$27,Selections!$G$6:$G$27,"72h-six-markets-dc12-probability-odds-net-ev15-v9") -> 0 | Q21: =IF(P21<30,"Collect more scored forecasts (n="&P21&").",IF(O21>0.1,"Review overconfidence on a future holdout.",IF(K21<0,"Review prices and EV on a future holdout.","Continue forward testing. No automatic model change."))) -> Collect more scored forecasts (n=0).
A22: Policy | B22: 72h-ucl-v3 | C22: =COUNTIFS(Selections!$G$6:$G$27,"72h-ucl-v3") -> 8 | D22: =(COUNTIFS(Selections!$G$6:$G$27,"72h-ucl-v3",Selections!$K$6:$K$27,"WON")+COUNTIFS(Selections!$G$6:$G$27,"72h-ucl-v3",Selections!$K$6:$K$27,"LOST")) -> 6 | E22: =COUNTIFS(Selections!$G$6:$G$27,"72h-ucl-v3",Selections!$K$6:$K$27,"WON") -> 5 | F22: =COUNTIFS(Selections!$G$6:$G$27,"72h-ucl-v3",Selections!$K$6:$K$27,"LOST") -> 1 | G22: =COUNTIFS(Selections!$G$6:$G$27,"72h-ucl-v3")-(COUNTIFS(Selections!$G$6:$G$27,"72h-ucl-v3",Selections!$K$6:$K$27,"WON")+COUNTIFS(Selections!$G$6:$G$27,"72h-ucl-v3",Selections!$K$6:$K$27,"LOST")) -> 2 | H22: =IF((COUNTIFS(Selections!$G$6:$G$27,"72h-ucl-v3",Selections!$K$6:$K$27,"WON")+COUNTIFS(Selections!$G$6:$G$27,"72h-ucl-v3",Selections!$K$6:$K$27,"LOST"))=0,"n.a.",COUNTIFS(Selections!$G$6:$G$27,"72h-ucl-v3",Selections!$K$6:$K$27,"WON")/(COUNTIFS(Selections!$G$6:$G$27,"72h-ucl-v3",Selections!$K$6:$K$27,"WON")+COUNTIFS(Selections!$G$6:$G$27,"72h-ucl-v3",Selections!$K$6:$K$27,"LOST"))) -> 0.83333333 | I22: =SUMIFS(Selections!$M$6:$M$27,Selections!$G$6:$G$27,"72h-ucl-v3") -> 6 | J22: =SUMIFS(Selections!$N$6:$N$27,Selections!$G$6:$G$27,"72h-ucl-v3") -> 0.96 | K22: =IF(SUMIFS(Selections!$M$6:$M$27,Selections!$G$6:$G$27,"72h-ucl-v3")=0,"n.a.",SUMIFS(Selections!$N$6:$N$27,Selections!$G$6:$G$27,"72h-ucl-v3")/SUMIFS(Selections!$M$6:$M$27,Selections!$G$6:$G$27,"72h-ucl-v3")) -> 0.16 | L22: =IF(SUMIFS(Selections!$T$6:$T$27,Selections!$G$6:$G$27,"72h-ucl-v3")=0,"n.a.",SUMIFS(Selections!$O$6:$O$27,Selections!$G$6:$G$27,"72h-ucl-v3")/SUMIFS(Selections!$T$6:$T$27,Selections!$G$6:$G$27,"72h-ucl-v3")) -> 0.13798222 | M22: =IF(SUMIFS(Selections!$T$6:$T$27,Selections!$G$6:$G$27,"72h-ucl-v3")=0,"n.a.",SUMIFS(Selections!$S$6:$S$27,Selections!$G$6:$G$27,"72h-ucl-v3")/SUMIFS(Selections!$T$6:$T$27,Selections!$G$6:$G$27,"72h-ucl-v3")) -> 0.79429493 | N22: =IF(SUMIFS(Selections!$T$6:$T$27,Selections!$G$6:$G$27,"72h-ucl-v3")=0,"n.a.",(SUMIFS(Selections!$L$6:$L$27,Selections!$G$6:$G$27,"72h-ucl-v3",Selections!$T$6:$T$27,1))/SUMIFS(Selections!$T$6:$T$27,Selections!$G$6:$G$27,"72h-ucl-v3")) -> 0.83333333 | O22: =IF(SUMIFS(Selections!$T$6:$T$27,Selections!$G$6:$G$27,"72h-ucl-v3")=0,"n.a.",(SUMIFS(Selections!$S$6:$S$27,Selections!$G$6:$G$27,"72h-ucl-v3")-(SUMIFS(Selections!$L$6:$L$27,Selections!$G$6:$G$27,"72h-ucl-v3",Selections!$T$6:$T$27,1)))/SUMIFS(Selections!$T$6:$T$27,Selections!$G$6:$G$27,"72h-ucl-v3")) -> -0.039038406 | P22: =SUMIFS(Selections!$T$6:$T$27,Selections!$G$6:$G$27,"72h-ucl-v3") -> 6 | Q22: =IF(P22<30,"Collect more scored forecasts (n="&P22&").",IF(O22>0.1,"Review overconfidence on a future holdout.",IF(K22<0,"Review prices and EV on a future holdout.","Continue forward testing. No automatic model change."))) -> Collect more scored forecasts (n=6).
A23: Policy | B23: legacy/unspecified | C23: =COUNTIFS(Selections!$G$6:$G$27,"legacy/unspecified") -> 11 | D23: =(COUNTIFS(Selections!$G$6:$G$27,"legacy/unspecified",Selections!$K$6:$K$27,"WON")+COUNTIFS(Selections!$G$6:$G$27,"legacy/unspecified",Selections!$K$6:$K$27,"LOST")) -> 5 | E23: =COUNTIFS(Selections!$G$6:$G$27,"legacy/unspecified",Selections!$K$6:$K$27,"WON") -> 3 | F23: =COUNTIFS(Selections!$G$6:$G$27,"legacy/unspecified",Selections!$K$6:$K$27,"LOST") -> 2 | G23: =COUNTIFS(Selections!$G$6:$G$27,"legacy/unspecified")-(COUNTIFS(Selections!$G$6:$G$27,"legacy/unspecified",Selections!$K$6:$K$27,"WON")+COUNTIFS(Selections!$G$6:$G$27,"legacy/unspecified",Selections!$K$6:$K$27,"LOST")) -> 6 | H23: =IF((COUNTIFS(Selections!$G$6:$G$27,"legacy/unspecified",Selections!$K$6:$K$27,"WON")+COUNTIFS(Selections!$G$6:$G$27,"legacy/unspecified",Selections!$K$6:$K$27,"LOST"))=0,"n.a.",COUNTIFS(Selections!$G$6:$G$27,"legacy/unspecified",Selections!$K$6:$K$27,"WON")/(COUNTIFS(Selections!$G$6:$G$27,"legacy/unspecified",Selections!$K$6:$K$27,"WON")+COUNTIFS(Selections!$G$6:$G$27,"legacy/unspecified",Selections!$K$6:$K$27,"LOST"))) -> 0.6 | I23: =SUMIFS(Selections!$M$6:$M$27,Selections!$G$6:$G$27,"legacy/unspecified") -> 5 | J23: =SUMIFS(Selections!$N$6:$N$27,Selections!$G$6:$G$27,"legacy/unspecified") -> -0.85 | K23: =IF(SUMIFS(Selections!$M$6:$M$27,Selections!$G$6:$G$27,"legacy/unspecified")=0,"n.a.",SUMIFS(Selections!$N$6:$N$27,Selections!$G$6:$G$27,"legacy/unspecified")/SUMIFS(Selections!$M$6:$M$27,Selections!$G$6:$G$27,"legacy/unspecified")) -> -0.17 | L23: =IF(SUMIFS(Selections!$T$6:$T$27,Selections!$G$6:$G$27,"legacy/unspecified")=0,"n.a.",SUMIFS(Selections!$O$6:$O$27,Selections!$G$6:$G$27,"legacy/unspecified")/SUMIFS(Selections!$T$6:$T$27,Selections!$G$6:$G$27,"legacy/unspecified")) -> 0.30947166 | M23: =IF(SUMIFS(Selections!$T$6:$T$27,Selections!$G$6:$G$27,"legacy/unspecified")=0,"n.a.",SUMIFS(Selections!$S$6:$S$27,Selections!$G$6:$G$27,"legacy/unspecified")/SUMIFS(Selections!$T$6:$T$27,Selections!$G$6:$G$27,"legacy/unspecified")) -> 0.80970224 | N23: =IF(SUMIFS(Selections!$T$6:$T$27,Selections!$G$6:$G$27,"legacy/unspecified")=0,"n.a.",(SUMIFS(Selections!$L$6:$L$27,Selections!$G$6:$G$27,"legacy/unspecified",Selections!$T$6:$T$27,1))/SUMIFS(Selections!$T$6:$T$27,Selections!$G$6:$G$27,"legacy/unspecified")) -> 0.6 | O23: =IF(SUMIFS(Selections!$T$6:$T$27,Selections!$G$6:$G$27,"legacy/unspecified")=0,"n.a.",(SUMIFS(Selections!$S$6:$S$27,Selections!$G$6:$G$27,"legacy/unspecified")-(SUMIFS(Selections!$L$6:$L$27,Selections!$G$6:$G$27,"legacy/unspecified",Selections!$T$6:$T$27,1)))/SUMIFS(Selections!$T$6:$T$27,Selections!$G$6:$G$27,"legacy/unspecified")) -> 0.20970224 | P23: =SUMIFS(Selections!$T$6:$T$27,Selections!$G$6:$G$27,"legacy/unspecified") -> 5 | Q23: =IF(P23<30,"Collect more scored forecasts (n="&P23&").",IF(O23>0.1,"Review overconfidence on a future holdout.",IF(K23<0,"Review prices and EV on a future holdout.","Continue forward testing. No automatic model change."))) -> Collect more scored forecasts (n=5).
A24: Week | B24: 2026-W41 | C24: =COUNTIFS(Selections!$P$6:$P$27,"2026-W41") -> 5 | D24: =(COUNTIFS(Selections!$P$6:$P$27,"2026-W41",Selections!$K$6:$K$27,"WON")+COUNTIFS(Selections!$P$6:$P$27,"2026-W41",Selections!$K$6:$K$27,"LOST")) -> 4 | E24: =COUNTIFS(Selections!$P$6:$P$27,"2026-W41",Selections!$K$6:$K$27,"WON") -> 2 | F24: =COUNTIFS(Selections!$P$6:$P$27,"2026-W41",Selections!$K$6:$K$27,"LOST") -> 2 | G24: =COUNTIFS(Selections!$P$6:$P$27,"2026-W41")-(COUNTIFS(Selections!$P$6:$P$27,"2026-W41",Selections!$K$6:$K$27,"WON")+COUNTIFS(Selections!$P$6:$P$27,"2026-W41",Selections!$K$6:$K$27,"LOST")) -> 1 | H24: =IF((COUNTIFS(Selections!$P$6:$P$27,"2026-W41",Selections!$K$6:$K$27,"WON")+COUNTIFS(Selections!$P$6:$P$27,"2026-W41",Selections!$K$6:$K$27,"LOST"))=0,"n.a.",COUNTIFS(Selections!$P$6:$P$27,"2026-W41",Selections!$K$6:$K$27,"WON")/(COUNTIFS(Selections!$P$6:$P$27,"2026-W41",Selections!$K$6:$K$27,"WON")+COUNTIFS(Selections!$P$6:$P$27,"2026-W41",Selections!$K$6:$K$27,"LOST"))) -> 0.5 | I24: =SUMIFS(Selections!$M$6:$M$27,Selections!$P$6:$P$27,"2026-W41") -> 4 | J24: =SUMIFS(Selections!$N$6:$N$27,Selections!$P$6:$P$27,"2026-W41") -> -1.48 | K24: =IF(SUMIFS(Selections!$M$6:$M$27,Selections!$P$6:$P$27,"2026-W41")=0,"n.a.",SUMIFS(Selections!$N$6:$N$27,Selections!$P$6:$P$27,"2026-W41")/SUMIFS(Selections!$M$6:$M$27,Selections!$P$6:$P$27,"2026-W41")) -> -0.37 | L24: =IF(SUMIFS(Selections!$T$6:$T$27,Selections!$P$6:$P$27,"2026-W41")=0,"n.a.",SUMIFS(Selections!$O$6:$O$27,Selections!$P$6:$P$27,"2026-W41")/SUMIFS(Selections!$T$6:$T$27,Selections!$P$6:$P$27,"2026-W41")) -> 0.32911599 | M24: =IF(SUMIFS(Selections!$T$6:$T$27,Selections!$P$6:$P$27,"2026-W41")=0,"n.a.",SUMIFS(Selections!$S$6:$S$27,Selections!$P$6:$P$27,"2026-W41")/SUMIFS(Selections!$T$6:$T$27,Selections!$P$6:$P$27,"2026-W41")) -> 0.82114857 | N24: =IF(SUMIFS(Selections!$T$6:$T$27,Selections!$P$6:$P$27,"2026-W41")=0,"n.a.",(SUMIFS(Selections!$L$6:$L$27,Selections!$P$6:$P$27,"2026-W41",Selections!$T$6:$T$27,1))/SUMIFS(Selections!$T$6:$T$27,Selections!$P$6:$P$27,"2026-W41")) -> 0.5 | O24: =IF(SUMIFS(Selections!$T$6:$T$27,Selections!$P$6:$P$27,"2026-W41")=0,"n.a.",(SUMIFS(Selections!$S$6:$S$27,Selections!$P$6:$P$27,"2026-W41")-(SUMIFS(Selections!$L$6:$L$27,Selections!$P$6:$P$27,"2026-W41",Selections!$T$6:$T$27,1)))/SUMIFS(Selections!$T$6:$T$27,Selections!$P$6:$P$27,"2026-W41")) -> 0.32114857 | P24: =SUMIFS(Selections!$T$6:$T$27,Selections!$P$6:$P$27,"2026-W41") -> 4 | Q24: =IF(P24<30,"Collect more scored forecasts (n="&P24&").",IF(O24>0.1,"Review overconfidence on a future holdout.",IF(K24<0,"Review prices and EV on a future holdout.","Continue forward testing. No automatic model change."))) -> Collect more scored forecasts (n=4).
A25: Week | B25: 2026-W42 | C25: =COUNTIFS(Selections!$P$6:$P$27,"2026-W42") -> 16 | D25: =(COUNTIFS(Selections!$P$6:$P$27,"2026-W42",Selections!$K$6:$K$27,"WON")+COUNTIFS(Selections!$P$6:$P$27,"2026-W42",Selections!$K$6:$K$27,"LOST")) -> 7 | E25: =COUNTIFS(Selections!$P$6:$P$27,"2026-W42",Selections!$K$6:$K$27,"WON") -> 6 | F25: =COUNTIFS(Selections!$P$6:$P$27,"2026-W42",Selections!$K$6:$K$27,"LOST") -> 1 | G25: =COUNTIFS(Selections!$P$6:$P$27,"2026-W42")-(COUNTIFS(Selections!$P$6:$P$27,"2026-W42",Selections!$K$6:$K$27,"WON")+COUNTIFS(Selections!$P$6:$P$27,"2026-W42",Selections!$K$6:$K$27,"LOST")) -> 9 | H25: =IF((COUNTIFS(Selections!$P$6:$P$27,"2026-W42",Selections!$K$6:$K$27,"WON")+COUNTIFS(Selections!$P$6:$P$27,"2026-W42",Selections!$K$6:$K$27,"LOST"))=0,"n.a.",COUNTIFS(Selections!$P$6:$P$27,"2026-W42",Selections!$K$6:$K$27,"WON")/(COUNTIFS(Selections!$P$6:$P$27,"2026-W42",Selections!$K$6:$K$27,"WON")+COUNTIFS(Selections!$P$6:$P$27,"2026-W42",Selections!$K$6:$K$27,"LOST"))) -> 0.85714286 | I25: =SUMIFS(Selections!$M$6:$M$27,Selections!$P$6:$P$27,"2026-W42") -> 7 | J25: =SUMIFS(Selections!$N$6:$N$27,Selections!$P$6:$P$27,"2026-W42") -> 1.59 | K25: =IF(SUMIFS(Selections!$M$6:$M$27,Selections!$P$6:$P$27,"2026-W42")=0,"n.a.",SUMIFS(Selections!$N$6:$N$27,Selections!$P$6:$P$27,"2026-W42")/SUMIFS(Selections!$M$6:$M$27,Selections!$P$6:$P$27,"2026-W42")) -> 0.22714286 | L25: =IF(SUMIFS(Selections!$T$6:$T$27,Selections!$P$6:$P$27,"2026-W42")=0,"n.a.",SUMIFS(Selections!$O$6:$O$27,Selections!$P$6:$P$27,"2026-W42")/SUMIFS(Selections!$T$6:$T$27,Selections!$P$6:$P$27,"2026-W42")) -> 0.15125538 | M25: =IF(SUMIFS(Selections!$T$6:$T$27,Selections!$P$6:$P$27,"2026-W42")=0,"n.a.",SUMIFS(Selections!$S$6:$S$27,Selections!$P$6:$P$27,"2026-W42")/SUMIFS(Selections!$T$6:$T$27,Selections!$P$6:$P$27,"2026-W42")) -> 0.78995521 | N25: =IF(SUMIFS(Selections!$T$6:$T$27,Selections!$P$6:$P$27,"2026-W42")=0,"n.a.",(SUMIFS(Selections!$L$6:$L$27,Selections!$P$6:$P$27,"2026-W42",Selections!$T$6:$T$27,1))/SUMIFS(Selections!$T$6:$T$27,Selections!$P$6:$P$27,"2026-W42")) -> 0.85714286 | O25: =IF(SUMIFS(Selections!$T$6:$T$27,Selections!$P$6:$P$27,"2026-W42")=0,"n.a.",(SUMIFS(Selections!$S$6:$S$27,Selections!$P$6:$P$27,"2026-W42")-(SUMIFS(Selections!$L$6:$L$27,Selections!$P$6:$P$27,"2026-W42",Selections!$T$6:$T$27,1)))/SUMIFS(Selections!$T$6:$T$27,Selections!$P$6:$P$27,"2026-W42")) -> -0.067187646 | P25: =SUMIFS(Selections!$T$6:$T$27,Selections!$P$6:$P$27,"2026-W42") -> 7 | Q25: =IF(P25<30,"Collect more scored forecasts (n="&P25&").",IF(O25>0.1,"Review overconfidence on a future holdout.",IF(K25<0,"Review prices and EV on a future holdout.","Continue forward testing. No automatic model change."))) -> Collect more scored forecasts (n=7).
A26: Week | B26: 2026-W43 | C26: =COUNTIFS(Selections!$P$6:$P$27,"2026-W43") -> 1 | D26: =(COUNTIFS(Selections!$P$6:$P$27,"2026-W43",Selections!$K$6:$K$27,"WON")+COUNTIFS(Selections!$P$6:$P$27,"2026-W43",Selections!$K$6:$K$27,"LOST")) -> 0 | E26: =COUNTIFS(Selections!$P$6:$P$27,"2026-W43",Selections!$K$6:$K$27,"WON") -> 0 | F26: =COUNTIFS(Selections!$P$6:$P$27,"2026-W43",Selections!$K$6:$K$27,"LOST") -> 0 | G26: =COUNTIFS(Selections!$P$6:$P$27,"2026-W43")-(COUNTIFS(Selections!$P$6:$P$27,"2026-W43",Selections!$K$6:$K$27,"WON")+COUNTIFS(Selections!$P$6:$P$27,"2026-W43",Selections!$K$6:$K$27,"LOST")) -> 1 | H26: =IF((COUNTIFS(Selections!$P$6:$P$27,"2026-W43",Selections!$K$6:$K$27,"WON")+COUNTIFS(Selections!$P$6:$P$27,"2026-W43",Selections!$K$6:$K$27,"LOST"))=0,"n.a.",COUNTIFS(Selections!$P$6:$P$27,"2026-W43",Selections!$K$6:$K$27,"WON")/(COUNTIFS(Selections!$P$6:$P$27,"2026-W43",Selections!$K$6:$K$27,"WON")+COUNTIFS(Selections!$P$6:$P$27,"2026-W43",Selections!$K$6:$K$27,"LOST"))) -> n.a. | I26: =SUMIFS(Selections!$M$6:$M$27,Selections!$P$6:$P$27,"2026-W43") -> 0 | J26: =SUMIFS(Selections!$N$6:$N$27,Selections!$P$6:$P$27,"2026-W43") -> 0 | K26: =IF(SUMIFS(Selections!$M$6:$M$27,Selections!$P$6:$P$27,"2026-W43")=0,"n.a.",SUMIFS(Selections!$N$6:$N$27,Selections!$P$6:$P$27,"2026-W43")/SUMIFS(Selections!$M$6:$M$27,Selections!$P$6:$P$27,"2026-W43")) -> n.a. | L26: =IF(SUMIFS(Selections!$T$6:$T$27,Selections!$P$6:$P$27,"2026-W43")=0,"n.a.",SUMIFS(Selections!$O$6:$O$27,Selections!$P$6:$P$27,"2026-W43")/SUMIFS(Selections!$T$6:$T$27,Selections!$P$6:$P$27,"2026-W43")) -> n.a. | M26: =IF(SUMIFS(Selections!$T$6:$T$27,Selections!$P$6:$P$27,"2026-W43")=0,"n.a.",SUMIFS(Selections!$S$6:$S$27,Selections!$P$6:$P$27,"2026-W43")/SUMIFS(Selections!$T$6:$T$27,Selections!$P$6:$P$27,"2026-W43")) -> n.a. | N26: =IF(SUMIFS(Selections!$T$6:$T$27,Selections!$P$6:$P$27,"2026-W43")=0,"n.a.",(SUMIFS(Selections!$L$6:$L$27,Selections!$P$6:$P$27,"2026-W43",Selections!$T$6:$T$27,1))/SUMIFS(Selections!$T$6:$T$27,Selections!$P$6:$P$27,"2026-W43")) -> n.a. | O26: =IF(SUMIFS(Selections!$T$6:$T$27,Selections!$P$6:$P$27,"2026-W43")=0,"n.a.",(SUMIFS(Selections!$S$6:$S$27,Selections!$P$6:$P$27,"2026-W43")-(SUMIFS(Selections!$L$6:$L$27,Selections!$P$6:$P$27,"2026-W43",Selections!$T$6:$T$27,1)))/SUMIFS(Selections!$T$6:$T$27,Selections!$P$6:$P$27,"2026-W43")) -> n.a. | P26: =SUMIFS(Selections!$T$6:$T$27,Selections!$P$6:$P$27,"2026-W43") -> 0 | Q26: =IF(P26<30,"Collect more scored forecasts (n="&P26&").",IF(O26>0.1,"Review overconfidence on a future holdout.",IF(K26<0,"Review prices and EV on a future holdout.","Continue forward testing. No automatic model change."))) -> Collect more scored forecasts (n=0).

Sheet Calibration
A2: Calibration
A4: Calibration compares scored forecast probabilities with observed outcomes. Small bins remain provisional evidence.
A5: Probability band | B5: Lower bound | C5: Upper bound | D5: Samples | E5: Mean forecast | F5: Observed win rate | G5: Overconfidence | H5: Binary Brier | I5: Review
A6: 0%–50% | B6: 0 | C6: 0.5 | D6: =COUNTIFS(Selections!$S$6:$S$27,">="&B6,Selections!$S$6:$S$27,"<"&C6,Selections!$T$6:$T$27,1) -> 0 | E6: =IF(D6=0,"n.a.",SUMIFS(Selections!$S$6:$S$27,Selections!$S$6:$S$27,">="&B6,Selections!$S$6:$S$27,"<"&C6,Selections!$T$6:$T$27,1)/D6) -> n.a. | F6: =IF(D6=0,"n.a.",SUMIFS(Selections!$L$6:$L$27,Selections!$S$6:$S$27,">="&B6,Selections!$S$6:$S$27,"<"&C6,Selections!$T$6:$T$27,1)/D6) -> n.a. | G6: =IF(D6=0,"n.a.",E6-F6) -> n.a. | H6: =IF(D6=0,"n.a.",SUMIFS(Selections!$O$6:$O$27,Selections!$S$6:$S$27,">="&B6,Selections!$S$6:$S$27,"<"&C6,Selections!$T$6:$T$27,1)/D6) -> n.a. | I6: Collect more scored forecasts (n=0).
A7: 50%–60% | B7: 0.5 | C7: 0.6 | D7: =COUNTIFS(Selections!$S$6:$S$27,">="&B7,Selections!$S$6:$S$27,"<"&C7,Selections!$T$6:$T$27,1) -> 0 | E7: =IF(D7=0,"n.a.",SUMIFS(Selections!$S$6:$S$27,Selections!$S$6:$S$27,">="&B7,Selections!$S$6:$S$27,"<"&C7,Selections!$T$6:$T$27,1)/D7) -> n.a. | F7: =IF(D7=0,"n.a.",SUMIFS(Selections!$L$6:$L$27,Selections!$S$6:$S$27,">="&B7,Selections!$S$6:$S$27,"<"&C7,Selections!$T$6:$T$27,1)/D7) -> n.a. | G7: =IF(D7=0,"n.a.",E7-F7) -> n.a. | H7: =IF(D7=0,"n.a.",SUMIFS(Selections!$O$6:$O$27,Selections!$S$6:$S$27,">="&B7,Selections!$S$6:$S$27,"<"&C7,Selections!$T$6:$T$27,1)/D7) -> n.a. | I7: Collect more scored forecasts (n=0).
A8: 60%–70% | B8: 0.6 | C8: 0.7 | D8: =COUNTIFS(Selections!$S$6:$S$27,">="&B8,Selections!$S$6:$S$27,"<"&C8,Selections!$T$6:$T$27,1) -> 2 | E8: =IF(D8=0,"n.a.",SUMIFS(Selections!$S$6:$S$27,Selections!$S$6:$S$27,">="&B8,Selections!$S$6:$S$27,"<"&C8,Selections!$T$6:$T$27,1)/D8) -> 0.67291177 | F8: =IF(D8=0,"n.a.",SUMIFS(Selections!$L$6:$L$27,Selections!$S$6:$S$27,">="&B8,Selections!$S$6:$S$27,"<"&C8,Selections!$T$6:$T$27,1)/D8) -> 1 | G8: =IF(D8=0,"n.a.",E8-F8) -> -0.32708823 | H8: =IF(D8=0,"n.a.",SUMIFS(Selections!$O$6:$O$27,Selections!$S$6:$S$27,">="&B8,Selections!$S$6:$S$27,"<"&C8,Selections!$T$6:$T$27,1)/D8) -> 0.10707454 | I8: Collect more scored forecasts (n=2).
A9: 70%–80% | B9: 0.7 | C9: 0.8 | D9: =COUNTIFS(Selections!$S$6:$S$27,">="&B9,Selections!$S$6:$S$27,"<"&C9,Selections!$T$6:$T$27,1) -> 4 | E9: =IF(D9=0,"n.a.",SUMIFS(Selections!$S$6:$S$27,Selections!$S$6:$S$27,">="&B9,Selections!$S$6:$S$27,"<"&C9,Selections!$T$6:$T$27,1)/D9) -> 0.75980336 | F9: =IF(D9=0,"n.a.",SUMIFS(Selections!$L$6:$L$27,Selections!$S$6:$S$27,">="&B9,Selections!$S$6:$S$27,"<"&C9,Selections!$T$6:$T$27,1)/D9) -> 0.75 | G9: =IF(D9=0,"n.a.",E9-F9) -> 0.0098033603 | H9: =IF(D9=0,"n.a.",SUMIFS(Selections!$O$6:$O$27,Selections!$S$6:$S$27,">="&B9,Selections!$S$6:$S$27,"<"&C9,Selections!$T$6:$T$27,1)/D9) -> 0.18645173 | I9: Collect more scored forecasts (n=4).
A10: 80%–90% | B10: 0.8 | C10: 0.9 | D10: =COUNTIFS(Selections!$S$6:$S$27,">="&B10,Selections!$S$6:$S$27,"<"&C10,Selections!$T$6:$T$27,1) -> 3 | E10: =IF(D10=0,"n.a.",SUMIFS(Selections!$S$6:$S$27,Selections!$S$6:$S$27,">="&B10,Selections!$S$6:$S$27,"<"&C10,Selections!$T$6:$T$27,1)/D10) -> 0.85660101 | F10: =IF(D10=0,"n.a.",SUMIFS(Selections!$L$6:$L$27,Selections!$S$6:$S$27,">="&B10,Selections!$S$6:$S$27,"<"&C10,Selections!$T$6:$T$27,1)/D10) -> 0.33333333 | G10: =IF(D10=0,"n.a.",E10-F10) -> 0.52326767 | H10: =IF(D10=0,"n.a.",SUMIFS(Selections!$O$6:$O$27,Selections!$S$6:$S$27,">="&B10,Selections!$S$6:$S$27,"<"&C10,Selections!$T$6:$T$27,1)/D10) -> 0.46832387 | I10: Collect more scored forecasts (n=3).
A11: 90%–100% | B11: 0.9 | C11: 1.000001 | D11: =COUNTIFS(Selections!$S$6:$S$27,">="&B11,Selections!$S$6:$S$27,"<"&C11,Selections!$T$6:$T$27,1) -> 2 | E11: =IF(D11=0,"n.a.",SUMIFS(Selections!$S$6:$S$27,Selections!$S$6:$S$27,">="&B11,Selections!$S$6:$S$27,"<"&C11,Selections!$T$6:$T$27,1)/D11) -> 0.92972037 | F11: =IF(D11=0,"n.a.",SUMIFS(Selections!$L$6:$L$27,Selections!$S$6:$S$27,">="&B11,Selections!$S$6:$S$27,"<"&C11,Selections!$T$6:$T$27,1)/D11) -> 1 | G11: =IF(D11=0,"n.a.",E11-F11) -> -0.070279627 | H11: =IF(D11=0,"n.a.",SUMIFS(Selections!$O$6:$O$27,Selections!$S$6:$S$27,">="&B11,Selections!$S$6:$S$27,"<"&C11,Selections!$T$6:$T$27,1)/D11) -> 0.0051620049 | I11: Collect more scored forecasts (n=2).

Sheet Selections
A2: Selections | B2: Selections
A4: Frozen selections. Technical fields are grouped; expand them for source details. Kickoff times are UTC. | B4: Frozen selections. Technical fields are grouped; expand them for source details. Kickoff times are UTC.
A5: Fixture key | B5: Kickoff UTC | C5: League | D5: Match | E5: Market | F5: Tier | G5: Selection policy | H5: Adjusted probability | I5: Decimal odds | J5: Final score | K5: Status | L5: Won = 1 | M5: Stake units | N5: Profit units | O5: Binary Brier | P5: ISO week | Q5: Snapshot commit | R5: Result source | S5: Scored forecast | T5: Probability sample | U5: Cost per unit stake
A6: La Liga|elche|celta vigo|2026-10-11 | B6: 46306.5 | C6: La Liga | D6: Elche CF vs Celta Vigo | E6: Over 1.5 | F6: STRICT | G6: 72h-ucl-v3 | H6: 0.80135065 | I6: 1.35 | K6: UNVERIFIED_FIXTURE_OR_RESULT | M6: =IF(AND(ISNUMBER(L6),ISNUMBER(I6),I6>1),'ROI Plan'!$B$5,"") | N6: =IF(ISNUMBER(M6),M6*(I6*L6-1-U6),"") | O6: =IF(AND(ISNUMBER(L6),ISNUMBER(H6)),(H6-L6)^2,"") | P6: 2026-W41 | Q6: a2cdead106b513fd623cffd1e43a491685d68cc3 | S6: =IF(AND(ISNUMBER(L6),ISNUMBER(H6)),H6,"") | T6: =IF(AND(ISNUMBER(L6),ISNUMBER(H6)),1,0) -> 0 | U6: 0
A7: Premier League|crystal palace|nott m forest|2026-10-11 | B7: 46306.542 | C7: Premier League | D7: Crystal Palace vs Nottingham Forest | E7: Under 3.5 | F7: PROVISIONAL | G7: 72h-ucl-v3 | H7: 0.75512182 | I7: 1.39 | J7: 3-1 | K7: LOST | L7: 0 | M7: =IF(AND(ISNUMBER(L7),ISNUMBER(I7),I7>1),'ROI Plan'!$B$5,"") -> 1 | N7: =IF(ISNUMBER(M7),M7*(I7*L7-1-U7),"") -> -1 | O7: =IF(AND(ISNUMBER(L7),ISNUMBER(H7)),(H7-L7)^2,"") -> 0.57020896 | P7: 2026-W41 | Q7: a2cdead106b513fd623cffd1e43a491685d68cc3 | R7: football-data.org/v4 | S7: =IF(AND(ISNUMBER(L7),ISNUMBER(H7)),H7,"") -> 0.75512182 | T7: =IF(AND(ISNUMBER(L7),ISNUMBER(H7)),1,0) -> 1 | U7: 0
A8: Premier League|hull city|everton|2026-10-11 | B8: 46306.542 | C8: Premier League | D8: Hull City vs Everton | E8: Under 3.5 | F8: PROVISIONAL | G8: legacy/unspecified | H8: 0.83349958 | I8: 1.32 | J8: 2-2 | K8: LOST | L8: 0 | M8: =IF(AND(ISNUMBER(L8),ISNUMBER(I8),I8>1),'ROI Plan'!$B$5,"") -> 1 | N8: =IF(ISNUMBER(M8),M8*(I8*L8-1-U8),"") -> -1 | O8: =IF(AND(ISNUMBER(L8),ISNUMBER(H8)),(H8-L8)^2,"") -> 0.69472155 | P8: 2026-W41 | Q8: bdc690a8c70643c93f1595d53c067b7d91325270 | R8: football-data.org/v4 | S8: =IF(AND(ISNUMBER(L8),ISNUMBER(H8)),H8,"") -> 0.83349958 | T8: =IF(AND(ISNUMBER(L8),ISNUMBER(H8)),1,0) -> 1 | U8: 0
A9: Serie A|lecce|bologna|2026-10-11 | B9: 46306.542 | C9: Serie A | D9: Lecce vs Bologna | E9: Under 3.5 | F9: PROVISIONAL | G9: legacy/unspecified | H9: 0.79642477 | I9: 1.28 | J9: 1-2 | K9: WON | L9: 1 | M9: =IF(AND(ISNUMBER(L9),ISNUMBER(I9),I9>1),'ROI Plan'!$B$5,"") -> 1 | N9: =IF(ISNUMBER(M9),M9*(I9*L9-1-U9),"") -> 0.28 | O9: =IF(AND(ISNUMBER(L9),ISNUMBER(H9)),(H9-L9)^2,"") -> 0.041442876 | P9: 2026-W41 | Q9: bdc690a8c70643c93f1595d53c067b7d91325270 | R9: football-data.org/v4 | S9: =IF(AND(ISNUMBER(L9),ISNUMBER(H9)),H9,"") -> 0.79642477 | T9: =IF(AND(ISNUMBER(L9),ISNUMBER(H9)),1,0) -> 1 | U9: 0
A10: La Liga|real racing santander|valencia|2026-10-11 | B10: 46306.792 | C10: La Liga | D10: Real Racing Club de Santander vs Valencia | E10: Over 1.5 | F10: PROVISIONAL | G10: legacy/unspecified | H10: 0.89954811 | I10: 1.24 | J10: 2-2 | K10: WON | L10: 1 | M10: =IF(AND(ISNUMBER(L10),ISNUMBER(I10),I10>1),'ROI Plan'!$B$5,"") -> 1 | N10: =IF(ISNUMBER(M10),M10*(I10*L10-1-U10),"") -> 0.24 | O10: =IF(AND(ISNUMBER(L10),ISNUMBER(H10)),(H10-L10)^2,"") -> 0.010090582 | P10: 2026-W41 | Q10: bdc690a8c70643c93f1595d53c067b7d91325270 | R10: football-data.org/v4 | S10: =IF(AND(ISNUMBER(L10),ISNUMBER(H10)),H10,"") -> 0.89954811 | T10: =IF(AND(ISNUMBER(L10),ISNUMBER(H10)),1,0) -> 1 | U10: 0
A11: Serie A|atalanta bc|venezia|2026-10-12 | B11: 46307.688 | C11: Serie A | D11: Atalanta BC vs Venezia | E11: Home win | F11: STRICT | G11: legacy/unspecified | H11: 0.68228341 | I11: 1.63 | J11: 3-1 | K11: WON | L11: 1 | M11: =IF(AND(ISNUMBER(L11),ISNUMBER(I11),I11>1),'ROI Plan'!$B$5,"") -> 1 | N11: =IF(ISNUMBER(M11),M11*(I11*L11-1-U11),"") -> 0.63 | O11: =IF(AND(ISNUMBER(L11),ISNUMBER(H11)),(H11-L11)^2,"") -> 0.10094383 | P11: 2026-W42 | Q11: bdc690a8c70643c93f1595d53c067b7d91325270 | R11: football-data.org/v4 | S11: =IF(AND(ISNUMBER(L11),ISNUMBER(H11)),H11,"") -> 0.68228341 | T11: =IF(AND(ISNUMBER(L11),ISNUMBER(H11)),1,0) -> 1 | U11: 0
A12: La Liga|levante|sevilla|2026-10-12 | B12: 46307.792 | C12: La Liga | D12: Levante vs Sevilla | E12: Over 1.5 | F12: STRICT | G12: 72h-ucl-v3 | H12: 0.78199398 | I12: 1.34 | J12: 3-3 | K12: WON | L12: 1 | M12: =IF(AND(ISNUMBER(L12),ISNUMBER(I12),I12>1),'ROI Plan'!$B$5,"") -> 1 | N12: =IF(ISNUMBER(M12),M12*(I12*L12-1-U12),"") -> 0.34 | O12: =IF(AND(ISNUMBER(L12),ISNUMBER(H12)),(H12-L12)^2,"") -> 0.047526625 | P12: 2026-W42 | Q12: a2cdead106b513fd623cffd1e43a491685d68cc3 | R12: football-data.org/v4 | S12: =IF(AND(ISNUMBER(L12),ISNUMBER(H12)),H12,"") -> 0.78199398 | T12: =IF(AND(ISNUMBER(L12),ISNUMBER(H12)),1,0) -> 1 | U12: 0
A13: Premier League|coventry city|newcastle|2026-10-12 | B13: 46307.792 | C13: Premier League | D13: Coventry City vs Newcastle United | E13: Under 3.5 | F13: PROVISIONAL | G13: legacy/unspecified | H13: 0.83675533 | I13: 1.5 | J13: 4-1 | K13: LOST | L13: 0 | M13: =IF(AND(ISNUMBER(L13),ISNUMBER(I13),I13>1),'ROI Plan'!$B$5,"") -> 1 | N13: =IF(ISNUMBER(M13),M13*(I13*L13-1-U13),"") -> -1 | O13: =IF(AND(ISNUMBER(L13),ISNUMBER(H13)),(H13-L13)^2,"") -> 0.70015949 | P13: 2026-W42 | Q13: bdc690a8c70643c93f1595d53c067b7d91325270 | R13: football-data.org/v4 | S13: =IF(AND(ISNUMBER(L13),ISNUMBER(H13)),H13,"") -> 0.83675533 | T13: =IF(AND(ISNUMBER(L13),ISNUMBER(H13)),1,0) -> 1 | U13: 0
A14: UEFA Champions League|ath madrid|man united|2026-10-13 | B14: 46308.792 | C14: UEFA Champions League | D14: Atlético Madrid vs Manchester United | E14: Over 1.5 | F14: STRICT | G14: 72h-ucl-v3 | H14: 0.94464615 | I14: 1.15 | J14: 2-0 | K14: WON | L14: 1 | M14: =IF(AND(ISNUMBER(L14),ISNUMBER(I14),I14>1),'ROI Plan'!$B$5,"") -> 1 | N14: =IF(ISNUMBER(M14),M14*(I14*L14-1-U14),"") -> 0.15 | O14: =IF(AND(ISNUMBER(L14),ISNUMBER(H14)),(H14-L14)^2,"") -> 0.0030640483 | P14: 2026-W42 | Q14: a2cdead106b513fd623cffd1e43a491685d68cc3 | R14: football-data.org/v4 | S14: =IF(AND(ISNUMBER(L14),ISNUMBER(H14)),H14,"") -> 0.94464615 | T14: =IF(AND(ISNUMBER(L14),ISNUMBER(H14)),1,0) -> 1 | U14: 0
A15: UEFA Champions League|galatasaray|barcelona|2026-10-13 | B15: 46308.792 | C15: UEFA Champions League | D15: Galatasaray vs Barcelona | E15: Both Teams to Score - Yes | F15: STRICT | G15: 72h-ucl-v3 | H15: 0.70567288 | I15: 1.49 | J15: 1-4 | K15: WON | L15: 1 | M15: =IF(AND(ISNUMBER(L15),ISNUMBER(I15),I15>1),'ROI Plan'!$B$5,"") -> 1 | N15: =IF(ISNUMBER(M15),M15*(I15*L15-1-U15),"") -> 0.49 | O15: =IF(AND(ISNUMBER(L15),ISNUMBER(H15)),(H15-L15)^2,"") -> 0.086628456 | P15: 2026-W42 | Q15: a2cdead106b513fd623cffd1e43a491685d68cc3 | R15: football-data.org/v4 | S15: =IF(AND(ISNUMBER(L15),ISNUMBER(H15)),H15,"") -> 0.70567288 | T15: =IF(AND(ISNUMBER(L15),ISNUMBER(H15)),1,0) -> 1 | U15: 0
A16: UEFA Champions League|feyenoord|como|2026-10-14 | B16: 46309.698 | C16: UEFA Champions League | D16: Feyenoord vs Como | E16: Over 1.5 | F16: STRICT | G16: 72h-ucl-v3 | H16: 0.95580888 | I16: 1.14 | K16: UNVERIFIED_FIXTURE_OR_RESULT | M16: =IF(AND(ISNUMBER(L16),ISNUMBER(I16),I16>1),'ROI Plan'!$B$5,"") | N16: =IF(ISNUMBER(M16),M16*(I16*L16-1-U16),"") | O16: =IF(AND(ISNUMBER(L16),ISNUMBER(H16)),(H16-L16)^2,"") | P16: 2026-W42 | Q16: 4f7af2f470a0b5cdb7b8ae974c859f87b0236fc4 | S16: =IF(AND(ISNUMBER(L16),ISNUMBER(H16)),H16,"") | T16: =IF(AND(ISNUMBER(L16),ISNUMBER(H16)),1,0) -> 0 | U16: 0
A17: UEFA Champions League|aston villa|fenerbahce|2026-10-14 | B17: 46309.792 | C17: UEFA Champions League | D17: Aston Villa vs Fenerbahce | E17: Home win | F17: STRICT | G17: 72h-ucl-v3 | H17: 0.66354014 | I17: 1.74 | J17: 6-0 | K17: WON | L17: 1 | M17: =IF(AND(ISNUMBER(L17),ISNUMBER(I17),I17>1),'ROI Plan'!$B$5,"") -> 1 | N17: =IF(ISNUMBER(M17),M17*(I17*L17-1-U17),"") -> 0.74 | O17: =IF(AND(ISNUMBER(L17),ISNUMBER(H17)),(H17-L17)^2,"") -> 0.11320524 | P17: 2026-W42 | Q17: 4f7af2f470a0b5cdb7b8ae974c859f87b0236fc4 | R17: football-data.org/v4 | S17: =IF(AND(ISNUMBER(L17),ISNUMBER(H17)),H17,"") -> 0.66354014 | T17: =IF(AND(ISNUMBER(L17),ISNUMBER(H17)),1,0) -> 1 | U17: 0
A18: UEFA Champions League|real betis|porto|2026-10-14 | B18: 46309.792 | C18: UEFA Champions League | D18: Real Betis vs Porto | E18: Over 1.5 | F18: STRICT | G18: 72h-ucl-v3 | H18: 0.91479459 | I18: 1.24 | J18: 3-2 | K18: WON | L18: 1 | M18: =IF(AND(ISNUMBER(L18),ISNUMBER(I18),I18>1),'ROI Plan'!$B$5,"") -> 1 | N18: =IF(ISNUMBER(M18),M18*(I18*L18-1-U18),"") -> 0.24 | O18: =IF(AND(ISNUMBER(L18),ISNUMBER(H18)),(H18-L18)^2,"") -> 0.0072599614 | P18: 2026-W42 | Q18: 4f7af2f470a0b5cdb7b8ae974c859f87b0236fc4 | R18: football-data.org/v4 | S18: =IF(AND(ISNUMBER(L18),ISNUMBER(H18)),H18,"") -> 0.91479459 | T18: =IF(AND(ISNUMBER(L18),ISNUMBER(H18)),1,0) -> 1 | U18: 0
A19: La Liga|deportivo la coruna|levante|2026-10-16 | B19: 46311.792 | C19: La Liga | D19: Deportivo La Coruña vs Levante | E19: Over 1.5 | F19: STRICT | G19: 72h-all-markets-net-ev15-execution-v7 | H19: 0.84906777 | I19: 1.27 | K19: PENDING_KICKOFF_OR_FINAL_SCORE | M19: =IF(AND(ISNUMBER(L19),ISNUMBER(I19),I19>1),'ROI Plan'!$B$5,"") | N19: =IF(ISNUMBER(M19),M19*(I19*L19-1-U19),"") | O19: =IF(AND(ISNUMBER(L19),ISNUMBER(H19)),(H19-L19)^2,"") | P19: 2026-W42 | Q19: d3f12df5a2a20809c3ac84f9a31766ba965813e3 | S19: =IF(AND(ISNUMBER(L19),ISNUMBER(H19)),H19,"") | T19: =IF(AND(ISNUMBER(L19),ISNUMBER(H19)),1,0) -> 0 | U19: 0
A20: Serie A|venezia|napoli|2026-10-17 | B20: 46312.542 | C20: Serie A | D20: Venezia vs Napoli | E20: Away win | F20: STRICT | G20: 72h-all-markets-net-ev15-execution-v7 | H20: 0.66032355 | I20: 1.71 | K20: PENDING_KICKOFF_OR_FINAL_SCORE | M20: =IF(AND(ISNUMBER(L20),ISNUMBER(I20),I20>1),'ROI Plan'!$B$5,"") | N20: =IF(ISNUMBER(M20),M20*(I20*L20-1-U20),"") | O20: =IF(AND(ISNUMBER(L20),ISNUMBER(H20)),(H20-L20)^2,"") | P20: 2026-W42 | Q20: 54bb8a2c2c957dda77ef247b3e042f6a945bda8f | S20: =IF(AND(ISNUMBER(L20),ISNUMBER(H20)),H20,"") | T20: =IF(AND(ISNUMBER(L20),ISNUMBER(H20)),1,0) -> 0 | U20: 0
A21: Bundesliga|werder bremen|paderborn|2026-10-17 | B21: 46312.562 | C21: Bundesliga | D21: Werder Bremen vs SC Paderborn | E21: Double Chance 1X | F21: STRICT | G21: 72h-six-markets-dc12-probability-odds-net-ev15-v9 | H21: 0.80166338 | I21: 1.27 | K21: PENDING_KICKOFF_OR_FINAL_SCORE | M21: =IF(AND(ISNUMBER(L21),ISNUMBER(I21),I21>1),'ROI Plan'!$B$5,"") | N21: =IF(ISNUMBER(M21),M21*(I21*L21-1-U21),"") | O21: =IF(AND(ISNUMBER(L21),ISNUMBER(H21)),(H21-L21)^2,"") | P21: 2026-W42 | Q21: b57f98f7704eb71a9d1b11eddf359e66786ea2fe | S21: =IF(AND(ISNUMBER(L21),ISNUMBER(H21)),H21,"") | T21: =IF(AND(ISNUMBER(L21),ISNUMBER(H21)),1,0) -> 0 | U21: 0
A22: Premier League|fulham|hull city|2026-10-17 | B22: 46312.583 | C22: Premier League | D22: Fulham vs Hull City | E22: Under 3.5 | F22: PROVISIONAL | G22: legacy/unspecified | H22: 0.80219946 | I22: 1.42 | K22: PENDING_KICKOFF_OR_FINAL_SCORE | M22: =IF(AND(ISNUMBER(L22),ISNUMBER(I22),I22>1),'ROI Plan'!$B$5,"") | N22: =IF(ISNUMBER(M22),M22*(I22*L22-1-U22),"") | O22: =IF(AND(ISNUMBER(L22),ISNUMBER(H22)),(H22-L22)^2,"") | P22: 2026-W42 | Q22: bdc690a8c70643c93f1595d53c067b7d91325270 | S22: =IF(AND(ISNUMBER(L22),ISNUMBER(H22)),H22,"") | T22: =IF(AND(ISNUMBER(L22),ISNUMBER(H22)),1,0) -> 0 | U22: 0
A23: Premier League|man city|ipswich town|2026-10-17 | B23: 46312.583 | C23: Premier League | D23: Manchester City vs Ipswich Town | E23: Over 1.5 | F23: PROVISIONAL | G23: legacy/unspecified | H23: 0.91636212 | I23: 1.11 | K23: PENDING_KICKOFF_OR_FINAL_SCORE | M23: =IF(AND(ISNUMBER(L23),ISNUMBER(I23),I23>1),'ROI Plan'!$B$5,"") | N23: =IF(ISNUMBER(M23),M23*(I23*L23-1-U23),"") | O23: =IF(AND(ISNUMBER(L23),ISNUMBER(H23)),(H23-L23)^2,"") | P23: 2026-W42 | Q23: bdc690a8c70643c93f1595d53c067b7d91325270 | S23: =IF(AND(ISNUMBER(L23),ISNUMBER(H23)),H23,"") | T23: =IF(AND(ISNUMBER(L23),ISNUMBER(H23)),1,0) -> 0 | U23: 0
A24: La Liga|ca osasuna|real racing santander|2026-10-18 | B24: 46313.5 | C24: La Liga | D24: CA Osasuna vs Real Racing Club de Santander | E24: Over 1.5 | F24: PROVISIONAL | G24: legacy/unspecified | H24: 0.92026326 | I24: 1.22 | K24: PENDING_KICKOFF_OR_FINAL_SCORE | M24: =IF(AND(ISNUMBER(L24),ISNUMBER(I24),I24>1),'ROI Plan'!$B$5,"") | N24: =IF(ISNUMBER(M24),M24*(I24*L24-1-U24),"") | O24: =IF(AND(ISNUMBER(L24),ISNUMBER(H24)),(H24-L24)^2,"") | P24: 2026-W42 | Q24: bdc690a8c70643c93f1595d53c067b7d91325270 | S24: =IF(AND(ISNUMBER(L24),ISNUMBER(H24)),H24,"") | T24: =IF(AND(ISNUMBER(L24),ISNUMBER(H24)),1,0) -> 0 | U24: 0
A25: La Liga|malaga|real sociedad|2026-10-18 | B25: 46313.688 | C25: La Liga | D25: Málaga vs Real Sociedad | E25: Under 3.5 | F25: STRICT | G25: legacy/unspecified | H25: 0.82612478 | I25: 1.41 | K25: PENDING_KICKOFF_OR_FINAL_SCORE | M25: =IF(AND(ISNUMBER(L25),ISNUMBER(I25),I25>1),'ROI Plan'!$B$5,"") | N25: =IF(ISNUMBER(M25),M25*(I25*L25-1-U25),"") | O25: =IF(AND(ISNUMBER(L25),ISNUMBER(H25)),(H25-L25)^2,"") | P25: 2026-W42 | Q25: bdc690a8c70643c93f1595d53c067b7d91325270 | S25: =IF(AND(ISNUMBER(L25),ISNUMBER(H25)),H25,"") | T25: =IF(AND(ISNUMBER(L25),ISNUMBER(H25)),1,0) -> 0 | U25: 0
A26: La Liga|real madrid|sevilla|2026-10-18 | B26: 46313.792 | C26: La Liga | D26: Real Madrid vs Sevilla | E26: Home win | F26: PROVISIONAL | G26: legacy/unspecified | H26: 0.78842218 | I26: 1.3 | K26: PENDING_KICKOFF_OR_FINAL_SCORE | M26: =IF(AND(ISNUMBER(L26),ISNUMBER(I26),I26>1),'ROI Plan'!$B$5,"") | N26: =IF(ISNUMBER(M26),M26*(I26*L26-1-U26),"") | O26: =IF(AND(ISNUMBER(L26),ISNUMBER(H26)),(H26-L26)^2,"") | P26: 2026-W42 | Q26: bdc690a8c70643c93f1595d53c067b7d91325270 | S26: =IF(AND(ISNUMBER(L26),ISNUMBER(H26)),H26,"") | T26: =IF(AND(ISNUMBER(L26),ISNUMBER(H26)),1,0) -> 0 | U26: 0
A27: Premier League|tottenham|coventry city|2026-10-19 | B27: 46314.792 | C27: Premier League | D27: Tottenham Hotspur vs Coventry City | E27: Home win | F27: PROVISIONAL | G27: legacy/unspecified | H27: 0.66244119 | I27: 1.54 | K27: PENDING_KICKOFF_OR_FINAL_SCORE | M27: =IF(AND(ISNUMBER(L27),ISNUMBER(I27),I27>1),'ROI Plan'!$B$5,"") | N27: =IF(ISNUMBER(M27),M27*(I27*L27-1-U27),"") | O27: =IF(AND(ISNUMBER(L27),ISNUMBER(H27)),(H27-L27)^2,"") | P27: 2026-W43 | Q27: b9c15c09504aaf57de5ad0957adb91c0e9b37243 | S27: =IF(AND(ISNUMBER(L27),ISNUMBER(H27)),H27,"") | T27: =IF(AND(ISNUMBER(L27),ISNUMBER(H27)),1,0) -> 0 | U27: 0

Sheet Predictions
A2: Predictions | B2: Predictions
A4: Source: Git-frozen forecasts and football-data.org/v4 verified regulation-time results. | B4: Source: Git-frozen forecasts and football-data.org/v4 verified regulation-time results.
A5: Fixture key | B5: Kickoff UTC | C5: League | D5: Match | E5: Selection policy | F5: Status | G5: Final score | H5: 1X2 correct | I5: 1X2 Brier | J5: Over 1.5 correct | K5: Under 3.5 correct | L5: BTTS Yes correct | M5: BTTS No correct | N5: ISO week | O5: Snapshot commit | P5: Result source
A6: Serie A|como|as roma|2026-10-11 | B6: 46306.438 | C6: Serie A | D6: Como vs AS Roma | E6: legacy/unspecified | F6: UNVERIFIED_FIXTURE_OR_RESULT | N6: 2026-W41 | O6: 2fd31d33722311d8e0155bb5eca6b3a310ac938b
A7: La Liga|elche|celta vigo|2026-10-11 | B7: 46306.5 | C7: La Liga | D7: Elche CF vs Celta Vigo | E7: legacy/unspecified | F7: UNVERIFIED_FIXTURE_OR_RESULT | N7: 2026-W41 | O7: 2fd31d33722311d8e0155bb5eca6b3a310ac938b
A8: Ligue 1|nice|strasbourg|2026-10-11 | B8: 46306.542 | C8: Ligue 1 | D8: Nice vs Strasbourg | E8: legacy/unspecified | F8: GRADED | G8: 2-1 | H8: 1 | I8: 0.54540666 | J8: 1 | K8: 1 | L8: 1 | M8: 1 | N8: 2026-W41 | O8: 2fd31d33722311d8e0155bb5eca6b3a310ac938b | P8: football-data.org/v4
A9: Premier League|crystal palace|nott m forest|2026-10-11 | B9: 46306.542 | C9: Premier League | D9: Crystal Palace vs Nottingham Forest | E9: legacy/unspecified | F9: GRADED | G9: 3-1 | H9: 0 | I9: 0.62873666 | J9: 1 | K9: 0 | L9: 1 | M9: 1 | N9: 2026-W41 | O9: 2fd31d33722311d8e0155bb5eca6b3a310ac938b | P9: football-data.org/v4
A10: Premier League|hull city|everton|2026-10-11 | B10: 46306.542 | C10: Premier League | D10: Hull City vs Everton | E10: legacy/unspecified | F10: GRADED | G10: 2-2 | H10: 0 | I10: 0.70638787 | J10: 1 | K10: 0 | L10: 0 | M10: 0 | N10: 2026-W41 | O10: 2fd31d33722311d8e0155bb5eca6b3a310ac938b | P10: football-data.org/v4
A11: Serie A|lazio|monza|2026-10-11 | B11: 46306.542 | C11: Serie A | D11: Lazio vs Monza | E11: legacy/unspecified | F11: GRADED | G11: 3-1 | H11: 1 | I11: 0.2112717 | J11: 1 | K11: 0 | L11: 1 | M11: 1 | N11: 2026-W41 | O11: 2fd31d33722311d8e0155bb5eca6b3a310ac938b | P11: football-data.org/v4
A12: Serie A|lecce|bologna|2026-10-11 | B12: 46306.542 | C12: Serie A | D12: Lecce vs Bologna | E12: legacy/unspecified | F12: GRADED | G12: 1-2 | H12: 1 | I12: 0.37701409 | J12: 1 | K12: 1 | L12: 0 | M12: 0 | N12: 2026-W41 | O12: 2fd31d33722311d8e0155bb5eca6b3a310ac938b | P12: football-data.org/v4
A13: Bundesliga|1 koln|m gladbach|2026-10-11 | B13: 46306.562 | C13: Bundesliga | D13: 1. FC Köln vs Borussia Monchengladbach | E13: legacy/unspecified | F13: GRADED | G13: 2-1 | H13: 1 | I13: 0.54115992 | J13: 1 | K13: 1 | L13: 1 | M13: 1 | N13: 2026-W41 | O13: 2fd31d33722311d8e0155bb5eca6b3a310ac938b | P13: football-data.org/v4
A14: La Liga|real sociedad|deportivo la coruna|2026-10-11 | B14: 46306.594 | C14: La Liga | D14: Real Sociedad vs Deportivo La Coruña | E14: legacy/unspecified | F14: GRADED | G14: 3-2 | H14: 1 | I14: 0.35056735 | J14: 1 | K14: 0 | L14: 1 | M14: 1 | N14: 2026-W41 | O14: 2fd31d33722311d8e0155bb5eca6b3a310ac938b | P14: football-data.org/v4
A15: Ligue 1|rennes|auxerre|2026-10-11 | B15: 46306.635 | C15: Ligue 1 | D15: Rennes vs Auxerre | E15: legacy/unspecified | F15: UNVERIFIED_FIXTURE_OR_RESULT | N15: 2026-W41 | O15: 2fd31d33722311d8e0155bb5eca6b3a310ac938b
A16: Bundesliga|freiburg|schalke|2026-10-11 | B16: 46306.646 | C16: Bundesliga | D16: SC Freiburg vs FC Schalke 04 | E16: legacy/unspecified | F16: GRADED | G16: 2-1 | H16: 1 | I16: 0.42840131 | J16: 1 | K16: 1 | L16: 0 | M16: 0 | N16: 2026-W41 | O16: 2fd31d33722311d8e0155bb5eca6b3a310ac938b | P16: football-data.org/v4
A17: Premier League|liverpool|man city|2026-10-11 | B17: 46306.646 | C17: Premier League | D17: Liverpool vs Manchester City | E17: legacy/unspecified | F17: GRADED | G17: 0-3 | H17: 1 | I17: 0.5110281 | J17: 1 | K17: 1 | L17: 0 | M17: 0 | N17: 2026-W41 | O17: 2fd31d33722311d8e0155bb5eca6b3a310ac938b | P17: football-data.org/v4
A18: Serie A|sassuolo|milan|2026-10-11 | B18: 46306.667 | C18: Serie A | D18: Sassuolo vs AC Milan | E18: legacy/unspecified | F18: GRADED | G18: 1-1 | H18: 0 | I18: 0.89862621 | J18: 1 | K18: 1 | L18: 1 | M18: 1 | N18: 2026-W41 | O18: 2fd31d33722311d8e0155bb5eca6b3a310ac938b | P18: football-data.org/v4
A19: La Liga|real betis|ca osasuna|2026-10-11 | B19: 46306.688 | C19: La Liga | D19: Real Betis vs CA Osasuna | E19: legacy/unspecified | F19: GRADED | G19: 5-2 | H19: 1 | I19: 0.2459057 | J19: 1 | K19: 0 | L19: 1 | M19: 1 | N19: 2026-W41 | O19: 2fd31d33722311d8e0155bb5eca6b3a310ac938b | P19: football-data.org/v4
A20: Ligue 1|troyes|marseille|2026-10-11 | B20: 46306.781 | C20: Ligue 1 | D20: Troyes vs Marseille | E20: legacy/unspecified | F20: GRADED | G20: 0-2 | H20: 1 | I20: 0.2073436 | J20: 1 | K20: 1 | L20: 0 | M20: 0 | N20: 2026-W41 | O20: 2fd31d33722311d8e0155bb5eca6b3a310ac938b | P20: football-data.org/v4
A21: Serie A|cagliari|juventus|2026-10-11 | B21: 46306.781 | C21: Serie A | D21: Cagliari vs Juventus | E21: legacy/unspecified | F21: GRADED | G21: 1-1 | H21: 0 | I21: 0.9256308 | J21: 1 | K21: 1 | L21: 0 | M21: 0 | N21: 2026-W41 | O21: 2fd31d33722311d8e0155bb5eca6b3a310ac938b | P21: football-data.org/v4
A22: La Liga|real racing santander|valencia|2026-10-11 | B22: 46306.792 | C22: La Liga | D22: Real Racing Club de Santander vs Valencia | E22: legacy/unspecified | F22: GRADED | G22: 2-2 | H22: 0 | I22: 0.86201314 | J22: 1 | K22: 1 | L22: 1 | M22: 1 | N22: 2026-W41 | O22: 2fd31d33722311d8e0155bb5eca6b3a310ac938b | P22: football-data.org/v4
A23: Serie A|atalanta bc|venezia|2026-10-12 | B23: 46307.688 | C23: Serie A | D23: Atalanta BC vs Venezia | E23: legacy/unspecified | F23: GRADED | G23: 3-1 | H23: 1 | I23: 0.14951884 | J23: 1 | K23: 0 | L23: 0 | M23: 0 | N23: 2026-W42 | O23: 2fd31d33722311d8e0155bb5eca6b3a310ac938b | P23: football-data.org/v4
A24: Serie A|torino|udinese|2026-10-12 | B24: 46307.781 | C24: Serie A | D24: Torino vs Udinese | E24: legacy/unspecified | F24: GRADED | G24: 2-1 | H24: 1 | I24: 0.56760261 | J24: 1 | K24: 1 | L24: 1 | M24: 1 | N24: 2026-W42 | O24: 2fd31d33722311d8e0155bb5eca6b3a310ac938b | P24: football-data.org/v4
A25: La Liga|levante|sevilla|2026-10-12 | B25: 46307.792 | C25: La Liga | D25: Levante vs Sevilla | E25: legacy/unspecified | F25: GRADED | G25: 3-3 | H25: 0 | I25: 0.80099687 | J25: 1 | K25: 0 | L25: 1 | M25: 1 | N25: 2026-W42 | O25: 2fd31d33722311d8e0155bb5eca6b3a310ac938b | P25: football-data.org/v4
A26: Premier League|coventry city|newcastle|2026-10-12 | B26: 46307.792 | C26: Premier League | D26: Coventry City vs Newcastle United | E26: legacy/unspecified | F26: GRADED | G26: 4-1 | H26: 0 | I26: 1.0937054 | J26: 1 | K26: 0 | L26: 0 | M26: 0 | N26: 2026-W42 | O26: 2fd31d33722311d8e0155bb5eca6b3a310ac938b | P26: football-data.org/v4
A27: UEFA Champions League|rc lens|sporting cp|2026-10-13 | B27: 46308.698 | C27: UEFA Champions League | D27: RC Lens vs Sporting Lisbon | E27: legacy/unspecified | F27: GRADED | G27: 0-2 | H27: 1 | I27: 0.51245005 | J27: 1 | K27: 1 | L27: 0 | M27: 0 | N27: 2026-W42 | O27: 2fd31d33722311d8e0155bb5eca6b3a310ac938b | P27: football-data.org/v4
... A35: UEFA Champions League|villarreal|napoli|2026-10-13 | B35: 46308.792 | C35: UEFA Champions League | D35: Villarreal vs Napoli | E35: legacy/unspecified | F35: GRADED | G35: 3-1 | H35: 0 | I35: 0.67595769 | J35: 1 | K35: 0 | L35: 0 | M35: 0 | N35: 2026-W42 | O35: 2fd31d33722311d8e0155bb5eca6b3a310ac938b | P35: football-data.org/v4
A36: UEFA Champions League|feyenoord|como|2026-10-14 | B36: 46309.698 | C36: UEFA Champions League | D36: Feyenoord vs Como | E36: legacy/unspecified | F36: UNVERIFIED_FIXTURE_OR_RESULT | N36: 2026-W42 | O36: 2fd31d33722311d8e0155bb5eca6b3a310ac938b
A37: UEFA Champions League|lask|liverpool|2026-10-14 | B37: 46309.698 | C37: UEFA Champions League | D37: LASK vs Liverpool | E37: legacy/unspecified | F37: GRADED | G37: 3-6 | H37: 1 | I37: 0.11630855 | J37: 1 | K37: 0 | L37: 0 | M37: 0 | N37: 2026-W42 | O37: 2fd31d33722311d8e0155bb5eca6b3a310ac938b | P37: football-data.org/v4
A38: UEFA Champions League|as roma|real madrid|2026-10-14 | B38: 46309.792 | C38: UEFA Champions League | D38: AS Roma vs Real Madrid | E38: legacy/unspecified | F38: GRADED | G38: 3-4 | H38: 1 | I38: 0.35618254 | J38: 1 | K38: 0 | L38: 1 | M38: 1 | N38: 2026-W42 | O38: 2fd31d33722311d8e0155bb5eca6b3a310ac938b | P38: football-data.org/v4
A39: UEFA Champions League|aston villa|fenerbahce|2026-10-14 | B39: 46309.792 | C39: UEFA Champions League | D39: Aston Villa vs Fenerbahce | E39: legacy/unspecified | F39: GRADED | G39: 6-0 | H39: 1 | I39: 0.17457391 | J39: 1 | K39: 0 | L39: 1 | M39: 1 | N39: 2026-W42 | O39: 2fd31d33722311d8e0155bb5eca6b3a310ac938b | P39: football-data.org/v4
A40: UEFA Champions League|bod glimt|borussia dortmund|2026-10-14 | B40: 46309.792 | C40: UEFA Champions League | D40: Bodø/Glimt vs Borussia Dortmund | E40: legacy/unspecified | F40: GRADED | G40: 1-0 | H40: 0 | I40: 0.73892413 | J40: 0 | K40: 0 | L40: 0 | M40: 0 | N40: 2026-W42 | O40: 2fd31d33722311d8e0155bb5eca6b3a310ac938b | P40: football-data.org/v4
A41: UEFA Champions League|man city|paris sg|2026-10-14 | B41: 46309.792 | C41: UEFA Champions League | D41: Manchester City vs Paris Saint Germain | E41: legacy/unspecified | F41: GRADED | G41: 2-4 | H41: 1 | I41: 0.42849714 | J41: 1 | K41: 1 | L41: 1 | M41: 1 | N41: 2026-W42 | O41: 2fd31d33722311d8e0155bb5eca6b3a310ac938b | P41: football-data.org/v4
A42: UEFA Champions League|real betis|porto|2026-10-14 | B42: 46309.792 | C42: UEFA Champions League | D42: Real Betis vs Porto | E42: legacy/unspecified | F42: GRADED | G42: 3-2 | H42: 1 | I42: 0.18745153 | J42: 1 | K42: 1 | L42: 1 | M42: 1 | N42: 2026-W42 | O42: 2fd31d33722311d8e0155bb5eca6b3a310ac938b | P42: football-data.org/v4
A43: UEFA Champions League|shakhtar|aek athens|2026-10-14 | B43: 46309.792 | C43: UEFA Champions League | D43: Shakhtar Donetsk vs AEK Athens | E43: legacy/unspecified | F43: UNVERIFIED_FIXTURE_OR_RESULT | N43: 2026-W42 | O43: 2fd31d33722311d8e0155bb5eca6b3a310ac938b
A44: UEFA Champions League|sk slovan bratislava|vfb stuttgart|2026-10-14 | B44: 46309.792 | C44: UEFA Champions League | D44: ŠK Slovan Bratislava vs VfB Stuttgart | E44: legacy/unspecified | F44: GRADED | G44: 0-3 | H44: 1 | I44: 0.17832169 | J44: 1 | K44: 1 | L44: 0 | M44: 0 | N44: 2026-W42 | O44: 2fd31d33722311d8e0155bb5eca6b3a310ac938b | P44: football-data.org/v4
A45: Bundesliga|eintracht frankfurt|1 koln|2026-10-16 | B45: 46311.771 | C45: Bundesliga | D45: Eintracht Frankfurt vs 1. FC Köln | E45: legacy/unspecified | F45: PENDING_KICKOFF_OR_FINAL_SCORE | N45: 2026-W42 | O45: 2fd31d33722311d8e0155bb5eca6b3a310ac938b
A46: Ligue 1|le mans|toulouse|2026-10-16 | B46: 46311.781 | C46: Ligue 1 | D46: Le Mans FC vs Toulouse | E46: legacy/unspecified | F46: PENDING_KICKOFF_OR_FINAL_SCORE | N46: 2026-W42 | O46: 2fd31d33722311d8e0155bb5eca6b3a310ac938b
A47: Serie A|frosinone|sassuolo|2026-10-16 | B47: 46311.781 | C47: Serie A | D47: Frosinone vs Sassuolo | E47: legacy/unspecified | F47: PENDING_KICKOFF_OR_FINAL_SCORE | N47: 2026-W42 | O47: 2fd31d33722311d8e0155bb5eca6b3a310ac938b
A48: La Liga|deportivo la coruna|levante|2026-10-16 | B48: 46311.792 | C48: La Liga | D48: Deportivo La Coruña vs Levante | E48: legacy/unspecified | F48: PENDING_KICKOFF_OR_FINAL_SCORE | N48: 2026-W42 | O48: 2fd31d33722311d8e0155bb5eca6b3a310ac938b
A49: Premier League|everton|chelsea|2026-10-17 | B49: 46312.479 | C49: Premier League | D49: Everton vs Chelsea | E49: legacy/unspecified | F49: PENDING_KICKOFF_OR_FINAL_SCORE | N49: 2026-W42 | O49: 2fd31d33722311d8e0155bb5eca6b3a310ac938b
A50: La Liga|espanyol|ath madrid|2026-10-17 | B50: 46312.5 | C50: La Liga | D50: Espanyol vs Atlético Madrid | E50: legacy/unspecified | F50: PENDING_KICKOFF_OR_FINAL_SCORE | N50: 2026-W42 | O50: 2fd31d33722311d8e0155bb5eca6b3a310ac938b
A51: Serie A|venezia|napoli|2026-10-17 | B51: 46312.542 | C51: Serie A | D51: Venezia vs Napoli | E51: legacy/unspecified | F51: PENDING_KICKOFF_OR_FINAL_SCORE | N51: 2026-W42 | O51: 2fd31d33722311d8e0155bb5eca6b3a310ac938b
A52: Bundesliga|elversberg|augsburg|2026-10-17 | B52: 46312.562 | C52: Bundesliga | D52: Elversberg vs Augsburg | E52: legacy/unspecified | F52: PENDING_KICKOFF_OR_FINAL_SCORE | N52: 2026-W42 | O52: 2fd31d33722311d8e0155bb5eca6b3a310ac938b
A53: Bundesliga|hamburger|vfb stuttgart|2026-10-17 | B53: 46312.562 | C53: Bundesliga | D53: Hamburger SV vs VfB Stuttgart | E53: legacy/unspecified | F53: PENDING_KICKOFF_OR_FINAL_SCORE | N53: 2026-W42 | O53: 2fd31d33722311d8e0155bb5eca6b3a310ac938b
A54: Bundesliga|schalke|fsv mainz|2026-10-17 | B54: 46312.562 | C54: Bundesliga | D54: FC Schalke 04 vs FSV Mainz 05 | E54: legacy/unspecified | F54: PENDING_KICKOFF_OR_FINAL_SCORE | N54: 2026-W42 | O54: 2fd31d33722311d8e0155bb5eca6b3a310ac938b
A55: Bundesliga|union berlin|borussia dortmund|2026-10-17 | B55: 46312.562 | C55: Bundesliga | D55: Union Berlin vs Borussia Dortmund | E55: legacy/unspecified | F55: PENDING_KICKOFF_OR_FINAL_SCORE | N55: 2026-W42 | O55: 2fd31d33722311d8e0155bb5eca6b3a310ac938b
A56: Bundesliga|werder bremen|paderborn|2026-10-17 | B56: 46312.562 | C56: Bundesliga | D56: Werder Bremen vs SC Paderborn | E56: legacy/unspecified | F56: PENDING_KICKOFF_OR_FINAL_SCORE | N56: 2026-W42 | O56: 2fd31d33722311d8e0155bb5eca6b3a310ac938b
... A147: La Liga|ath bilbao|getafe|2026-10-25 | B147: 46320.542 | C147: La Liga | D147: Athletic Bilbao vs Getafe | E147: 72h-seven-markets-dc12-btts-probability-odds-net-ev15-v10 | F147: PENDING_KICKOFF_OR_FINAL_SCORE | N147: 2026-W43 | O147: 2db2af40cdce5284e5f00551472a6cbbd381dbcd

Sheet ROI Plan
A2: ROI Plan
A4: Starting bankroll (units) | B4: 100
A5: Flat stake per bet (units) | B5: 1
A7: Simulation in kickoff order. Separate flat stakes, no accumulators. Pending and missing-odds entries have no stake.
A9: Kickoff label | B9: Match | C9: Status | D9: Staked units | E9: Profit units | F9: Cumulative profit | G9: Simulated bankroll | H9: Peak bankroll | I9: Drawdown | J9: ISO week
A10: 2026-10-11T12:00:00+00:00 | B10: Elche CF vs Celta Vigo | C10: UNVERIFIED_FIXTURE_OR_RESULT | D10: =IF(ISNUMBER(Selections!M6),Selections!M6,"") | E10: =IF(ISNUMBER(Selections!N6),Selections!N6,"") | F10: =SUM($E$10:E10) -> 0 | G10: =$B$4+F10 -> 100 | H10: =MAX($B$4,$G$10:G10) -> 100 | I10: =H10-G10 -> 0 | J10: 2026-W41
A11: 2026-10-11T13:00:00+00:00 | B11: Crystal Palace vs Nottingham Forest | C11: LOST | D11: =IF(ISNUMBER(Selections!M7),Selections!M7,"") -> 1 | E11: =IF(ISNUMBER(Selections!N7),Selections!N7,"") -> -1 | F11: =SUM($E$10:E11) -> -1 | G11: =$B$4+F11 -> 99 | H11: =MAX($B$4,$G$10:G11) -> 100 | I11: =H11-G11 -> 1 | J11: 2026-W41
A12: 2026-10-11T13:00:00+00:00 | B12: Hull City vs Everton | C12: LOST | D12: =IF(ISNUMBER(Selections!M8),Selections!M8,"") -> 1 | E12: =IF(ISNUMBER(Selections!N8),Selections!N8,"") -> -1 | F12: =SUM($E$10:E12) -> -2 | G12: =$B$4+F12 -> 98 | H12: =MAX($B$4,$G$10:G12) -> 100 | I12: =H12-G12 -> 2 | J12: 2026-W41
A13: 2026-10-11T13:00:00+00:00 | B13: Lecce vs Bologna | C13: WON | D13: =IF(ISNUMBER(Selections!M9),Selections!M9,"") -> 1 | E13: =IF(ISNUMBER(Selections!N9),Selections!N9,"") -> 0.28 | F13: =SUM($E$10:E13) -> -1.72 | G13: =$B$4+F13 -> 98.28 | H13: =MAX($B$4,$G$10:G13) -> 100 | I13: =H13-G13 -> 1.72 | J13: 2026-W41
A14: 2026-10-11T19:00:00+00:00 | B14: Real Racing Club de Santander vs Valencia | C14: WON | D14: =IF(ISNUMBER(Selections!M10),Selections!M10,"") -> 1 | E14: =IF(ISNUMBER(Selections!N10),Selections!N10,"") -> 0.24 | F14: =SUM($E$10:E14) -> -1.48 | G14: =$B$4+F14 -> 98.52 | H14: =MAX($B$4,$G$10:G14) -> 100 | I14: =H14-G14 -> 1.48 | J14: 2026-W41
A15: 2026-10-12T16:30:00+00:00 | B15: Atalanta BC vs Venezia | C15: WON | D15: =IF(ISNUMBER(Selections!M11),Selections!M11,"") -> 1 | E15: =IF(ISNUMBER(Selections!N11),Selections!N11,"") -> 0.63 | F15: =SUM($E$10:E15) -> -0.85 | G15: =$B$4+F15 -> 99.15 | H15: =MAX($B$4,$G$10:G15) -> 100 | I15: =H15-G15 -> 0.85 | J15: 2026-W42
A16: 2026-10-12T19:00:00+00:00 | B16: Levante vs Sevilla | C16: WON | D16: =IF(ISNUMBER(Selections!M12),Selections!M12,"") -> 1 | E16: =IF(ISNUMBER(Selections!N12),Selections!N12,"") -> 0.34 | F16: =SUM($E$10:E16) -> -0.51 | G16: =$B$4+F16 -> 99.49 | H16: =MAX($B$4,$G$10:G16) -> 100 | I16: =H16-G16 -> 0.51 | J16: 2026-W42
A17: 2026-10-12T19:00:00+00:00 | B17: Coventry City vs Newcastle United | C17: LOST | D17: =IF(ISNUMBER(Selections!M13),Selections!M13,"") -> 1 | E17: =IF(ISNUMBER(Selections!N13),Selections!N13,"") -> -1 | F17: =SUM($E$10:E17) -> -1.51 | G17: =$B$4+F17 -> 98.49 | H17: =MAX($B$4,$G$10:G17) -> 100 | I17: =H17-G17 -> 1.51 | J17: 2026-W42
A18: 2026-10-13T19:00:00+00:00 | B18: Atlético Madrid vs Manchester United | C18: WON | D18: =IF(ISNUMBER(Selections!M14),Selections!M14,"") -> 1 | E18: =IF(ISNUMBER(Selections!N14),Selections!N14,"") -> 0.15 | F18: =SUM($E$10:E18) -> -1.36 | G18: =$B$4+F18 -> 98.64 | H18: =MAX($B$4,$G$10:G18) -> 100 | I18: =H18-G18 -> 1.36 | J18: 2026-W42
A19: 2026-10-13T19:00:00+00:00 | B19: Galatasaray vs Barcelona | C19: WON | D19: =IF(ISNUMBER(Selections!M15),Selections!M15,"") -> 1 | E19: =IF(ISNUMBER(Selections!N15),Selections!N15,"") -> 0.49 | F19: =SUM($E$10:E19) -> -0.87 | G19: =$B$4+F19 -> 99.13 | H19: =MAX($B$4,$G$10:G19) -> 100 | I19: =H19-G19 -> 0.87 | J19: 2026-W42
A20: 2026-10-14T16:45:00+00:00 | B20: Feyenoord vs Como | C20: UNVERIFIED_FIXTURE_OR_RESULT | D20: =IF(ISNUMBER(Selections!M16),Selections!M16,"") | E20: =IF(ISNUMBER(Selections!N16),Selections!N16,"") | F20: =SUM($E$10:E20) -> -0.87 | G20: =$B$4+F20 -> 99.13 | H20: =MAX($B$4,$G$10:G20) -> 100 | I20: =H20-G20 -> 0.87 | J20: 2026-W42
A21: 2026-10-14T19:00:00+00:00 | B21: Aston Villa vs Fenerbahce | C21: WON | D21: =IF(ISNUMBER(Selections!M17),Selections!M17,"") -> 1 | E21: =IF(ISNUMBER(Selections!N17),Selections!N17,"") -> 0.74 | F21: =SUM($E$10:E21) -> -0.13 | G21: =$B$4+F21 -> 99.87 | H21: =MAX($B$4,$G$10:G21) -> 100 | I21: =H21-G21 -> 0.13 | J21: 2026-W42
... A31: 2026-10-19T19:00:00+00:00 | B31: Tottenham Hotspur vs Coventry City | C31: PENDING_KICKOFF_OR_FINAL_SCORE | D31: =IF(ISNUMBER(Selections!M27),Selections!M27,"") | E31: =IF(ISNUMBER(Selections!N27),Selections!N27,"") | F31: =SUM($E$10:E31) -> 0.11 | G31: =$B$4+F31 -> 100.11 | H31: =MAX($B$4,$G$10:G31) -> 100.11 | I31: =H31-G31 -> 0 | J31: 2026-W43

Sheet Capture Details
A2: Forecast capture history
A4: Raw capture states are retained for diagnosing missing or failed experiment capture.
A5: Snapshot | B5: Captured UTC | C5: Goal-market blend | D5: Market-led forecasts | E5: Recency comparison | F5: EV filter sensitivity | G5: 85% market weight | H5: Pinnacle totals anchor | I5: Stronger regularisation (L2=3) | J5: Fixed half-life (480 days) | K5: Probability / calibration policy
A6: 2fd31d33722311d8e0155bb5eca6b3a310ac938b | B6: 2026-10-11T06:30:30Z | C6: LEGACY_NOT_RECORDED | D6: LEGACY_NOT_RECORDED | E6: LEGACY_NOT_RECORDED | F6: LEGACY_NOT_RECORDED | G6: LEGACY_NOT_RECORDED | H6: LEGACY_NOT_RECORDED | I6: LEGACY_NOT_RECORDED | J6: LEGACY_NOT_RECORDED | K6: LEGACY_NOT_RECORDED
A7: bdc690a8c70643c93f1595d53c067b7d91325270 | B7: 2026-10-11T06:38:09Z | C7: LEGACY_NOT_RECORDED | D7: LEGACY_NOT_RECORDED | E7: LEGACY_NOT_RECORDED | F7: LEGACY_NOT_RECORDED | G7: LEGACY_NOT_RECORDED | H7: LEGACY_NOT_RECORDED | I7: LEGACY_NOT_RECORDED | J7: LEGACY_NOT_RECORDED | K7: LEGACY_NOT_RECORDED
A8: b9c15c09504aaf57de5ad0957adb91c0e9b37243 | B8: 2026-10-11T06:44:04Z | C8: LEGACY_NOT_RECORDED | D8: LEGACY_NOT_RECORDED | E8: LEGACY_NOT_RECORDED | F8: LEGACY_NOT_RECORDED | G8: LEGACY_NOT_RECORDED | H8: LEGACY_NOT_RECORDED | I8: LEGACY_NOT_RECORDED | J8: LEGACY_NOT_RECORDED | K8: LEGACY_NOT_RECORDED
A9: 648ca5973f8d6521eefb8a4a5233fabb8e644a8e | B9: 2026-10-11T08:21:00Z | C9: LEGACY_NOT_RECORDED | D9: LEGACY_NOT_RECORDED | E9: LEGACY_NOT_RECORDED | F9: LEGACY_NOT_RECORDED | G9: LEGACY_NOT_RECORDED | H9: LEGACY_NOT_RECORDED | I9: LEGACY_NOT_RECORDED | J9: LEGACY_NOT_RECORDED | K9: LEGACY_NOT_RECORDED
A10: 660b75e4a3111f2a890ba1d58d595a637d01d0f2 | B10: 2026-10-11T08:25:02Z | C10: LEGACY_NOT_RECORDED | D10: LEGACY_NOT_RECORDED | E10: LEGACY_NOT_RECORDED | F10: LEGACY_NOT_RECORDED | G10: LEGACY_NOT_RECORDED | H10: LEGACY_NOT_RECORDED | I10: LEGACY_NOT_RECORDED | J10: LEGACY_NOT_RECORDED | K10: LEGACY_NOT_RECORDED
A11: a2cdead106b513fd623cffd1e43a491685d68cc3 | B11: 2026-10-11T10:46:00Z | C11: LEGACY_NOT_RECORDED | D11: LEGACY_NOT_RECORDED | E11: LEGACY_NOT_RECORDED | F11: LEGACY_NOT_RECORDED | G11: LEGACY_NOT_RECORDED | H11: LEGACY_NOT_RECORDED | I11: LEGACY_NOT_RECORDED | J11: LEGACY_NOT_RECORDED | K11: LEGACY_NOT_RECORDED
A12: 5fb257972ff233227b2e94d4b784eebf60b66d42 | B12: 2026-10-11T11:06:08Z | C12: LEGACY_NOT_RECORDED | D12: LEGACY_NOT_RECORDED | E12: LEGACY_NOT_RECORDED | F12: LEGACY_NOT_RECORDED | G12: LEGACY_NOT_RECORDED | H12: LEGACY_NOT_RECORDED | I12: LEGACY_NOT_RECORDED | J12: LEGACY_NOT_RECORDED | K12: LEGACY_NOT_RECORDED
A13: f1a72cc22d717088fb3c74014de8aae60f586e46 | B13: 2026-10-11T11:32:53Z | C13: LEGACY_NOT_RECORDED | D13: LEGACY_NOT_RECORDED | E13: LEGACY_NOT_RECORDED | F13: LEGACY_NOT_RECORDED | G13: LEGACY_NOT_RECORDED | H13: LEGACY_NOT_RECORDED | I13: LEGACY_NOT_RECORDED | J13: LEGACY_NOT_RECORDED | K13: LEGACY_NOT_RECORDED
A14: 4f7af2f470a0b5cdb7b8ae974c859f87b0236fc4 | B14: 2026-10-12T16:34:11Z | C14: LEGACY_NOT_RECORDED | D14: LEGACY_NOT_RECORDED | E14: LEGACY_NOT_RECORDED | F14: LEGACY_NOT_RECORDED | G14: LEGACY_NOT_RECORDED | H14: LEGACY_NOT_RECORDED | I14: LEGACY_NOT_RECORDED | J14: LEGACY_NOT_RECORDED | K14: LEGACY_NOT_RECORDED
A15: 5496e9ba03aeb2ae41363a329fbc48e9754cfb0e | B15: 2026-10-12T21:11:56Z | C15: LEGACY_NOT_RECORDED | D15: LEGACY_NOT_RECORDED | E15: LEGACY_NOT_RECORDED | F15: LEGACY_NOT_RECORDED | G15: LEGACY_NOT_RECORDED | H15: LEGACY_NOT_RECORDED | I15: LEGACY_NOT_RECORDED | J15: LEGACY_NOT_RECORDED | K15: LEGACY_NOT_RECORDED
A16: f6306ebd6d74a53df80194728284cbdc188f3667 | B16: 2026-10-13T07:01:01Z | C16: LEGACY_NOT_RECORDED | D16: LEGACY_NOT_RECORDED | E16: LEGACY_NOT_RECORDED | F16: LEGACY_NOT_RECORDED | G16: LEGACY_NOT_RECORDED | H16: LEGACY_NOT_RECORDED | I16: LEGACY_NOT_RECORDED | J16: LEGACY_NOT_RECORDED | K16: LEGACY_NOT_RECORDED
... A33: 2db2af40cdce5284e5f00551472a6cbbd381dbcd | B33: 2026-10-15T13:21:36Z | C33: CAPTURED | D33: CAPTURED | E33: CAPTURED | F33: CAPTURED | G33: CAPTURED | H33: CAPTURED | I33: LEGACY_NOT_RECORDED | J33: LEGACY_NOT_RECORDED | K33: CAPTURED

Sheet Metric Guide
A2: Metric guide
A4: Definitions apply to the archived forecasts and simulated selections in this workbook.
A5: Metric | B5: Meaning | C5: How to read it
A6: Win rate | B6: Wins divided by settled selections. Pending and unverified results are excluded. | C6: Read with the settled sample size and 95% interval.
A7: Simulated ROI | B7: Simulated net profit divided by staked units. Includes recorded per-stake costs. | C7: Offered prices and simulated stakes are not proof of actual returns. Missing prices are excluded.
A8: Binary Brier | B8: Mean squared error between a forecast probability and a binary outcome. | C8: Lower is better. Read the number of valid probability samples.
A9: 1X2 Brier | B9: Multiclass probability error across home win, draw and away win. | C9: Lower is better. Its scale differs from binary Brier; do not compare the two directly.
A10: Log loss | B10: Penalty assigned to the probability of the observed outcome. | C10: Lower is better. Compare candidates on the same fixtures.
A11: Calibration gap | B11: Mean forecast probability minus observed win rate on the same scored selections. | C11: Closer to zero is better. Positive indicates overconfidence; negative indicates underconfidence.
A12: Same-book offer CLV | B12: Frozen offered odds divided by observed near-close odds at the same bookmaker, minus one. | C12: Positive means a better earlier offered price. Quotes are not accepted prices or guaranteed official closing odds.
A13: Fair-close EV | B13: Frozen offered odds multiplied by the de-vigged near-close probability, minus one and recorded costs. | C13: Positive indicates value relative to that observed reference. Coverage must be shown.
A14: Verified coverage | B14: Share of verified in-scope fixtures with a usable paired candidate forecast. | C14: Use each versioned trial's registered minimum. Missing coverage remains unavailable.
A15: Initial review | B15: Original sidecars: at least 28 collection days and 30 settled observations. | C15: An initial look permits review, not promotion or a profitability claim.
A16: Approval review | B16: Versioned trials: registered fixture, ISO-week and coverage gates must pass. | C16: Readiness can include negative findings. Production changes require approval.
... A18: Unavailable / n.a. | B18: The required input or settled sample is missing. | C18: This is not a zero result and must not be interpreted as healthy evidence.
A21: Back to dashboard
